{"PhaseInfo":{"Sport":{"n_ID":[220],"n_TypeID":[3],"c_Name":["Cross-Country Skiing"],"c_Short":["CCS"]},"Event":{"n_ID":[10109],"n_TypeID":[1],"c_Name":["30km Freestyle"],"c_Short":["30km F"],"n_Sort":[200]},"Gender":{"n_ID":[2],"c_Name":["Women"],"c_Short":["W"]},"GenderEvent":{"n_ID":[5765],"c_Name":["Women's 30km Mass Start"],"c_Short":["Women's 30km Mass Start"]},"n_CompetitionSetID":[2],"n_SeasonID":[501],"n_Season":[20212022],"n_PhaseID":[1937873],"c_Phase":{},"n_PhaseNr":{},"n_PhaseEventTypeID":[1],"n_EventPhaseID":[1937873],"DateTimes":{"Start":{"c_Local":["2022-02-20T11:00:00"],"d_Local":["/Date(1645354800000+0000)/"],"n_Local":[20220220],"c_UTC":["2022-02-20T03:00:00"],"d_UTC":["/Date(1645326000000+0000)/"],"n_UTC":[20220220]},"End":{"c_Local":["2022-02-20T12:40:00"],"d_Local":["/Date(1645360800000+0000)/"],"n_Local":[20220220],"c_UTC":["2022-02-20T04:40:00"],"d_UTC":["/Date(1645332000000+0000)/"],"n_UTC":[20220220]}},"Venue":{"n_ID":[73854],"c_Name":["Zhangjiakou Cross-Country Centre"],"c_Short":{}},"Location":{"n_ID":[25216],"c_Name":["Zhangjiakou"],"c_Short":{}},"Country":{"n_ID":[2770],"c_Name":["China"],"c_Short":["CHN"]},"c_ScheduleStatus":["Finished"],"c_ResultStatus":["Official"],"c_ODF_ScheduleStatus":["FINISHED"],"c_ODF_ResultStatus":["OFFICIAL"],"b_Scheduled":[false],"b_StartList":[false],"b_InProgress":[false],"b_Finished":[true],"b_LiveWindow":[false],"b_Delayed":[false],"b_Postponed":[false],"b_Cancelled":[false],"b_Rescheduled":[false],"n_ParticipantsTotal":{},"n_ParticipantsCompleted":{},"CurrentResultPhase":{},"CourseInfoList":[]},"Medals":{"GoldMedals":[{"n_ParticipantType":1,"n_ParticipantID":656055,"c_Participant":"JOHAUG Therese","c_ParticipantShort":"JOHAUG T","c_ParticipantFirstName":"Therese","c_ParticipantLastName":"Johaug","c_Bib":"2","NOC":{"n_ID":153,"n_GeoID":2221,"c_Name":"Norway","c_Short":"NOR"},"TeamMemberList":[]}],"SilverMedals":[{"n_ParticipantType":1,"n_ParticipantID":774305,"c_Participant":"DIGGINS Jessie","c_ParticipantShort":"DIGGINS J","c_ParticipantFirstName":"Jessica","c_ParticipantLastName":"Diggins","c_Bib":"4","NOC":{"n_ID":5,"n_GeoID":2209,"c_Name":"United States","c_Short":"USA"},"TeamMemberList":[]}],"BronzeMedals":[{"n_ParticipantType":1,"n_ParticipantID":703248,"c_Participant":"NISKANEN Kerttu","c_ParticipantShort":"NISKANEN K","c_ParticipantFirstName":"Kerttu","c_ParticipantLastName":"Niskanen","c_Bib":"6","NOC":{"n_ID":161,"n_GeoID":2237,"c_Name":"Finland","c_Short":"FIN"},"TeamMemberList":[]}]},"Current":{"LastParticipant":{"n_ParticipantType":{},"n_ParticipantID":{},"c_Participant":{},"c_ParticipantShort":{},"c_ParticipantFirstName":{},"c_ParticipantLastName":{},"c_Bib":{},"n_StartOrder":{},"NOC":{"n_ID":{},"n_GeoID":{},"c_Name":{},"c_Short":{}},"TeamMemberList":[],"c_Rank":{},"c_Rank_Header":{},"c_Result":{},"c_Result_Header":{},"c_OverallRank":{},"c_OverallRank_Header":{},"c_OverallResult":{},"c_OverallResult_Header":{},"c_ResultInfo_1":{},"c_ResultInfo_1_Header":{},"c_ResultInfo_2":{},"c_ResultInfo_2_Header":{},"c_ResultInfo_3":{},"c_ResultInfo_3_Header":{},"c_ResultInfo_4":{},"c_ResultInfo_4_Header":{},"c_ResultInfo_5":{},"c_ResultInfo_5_Header":{},"c_ResultInfo_6":{},"c_ResultInfo_6_Header":{},"c_ResultInfo_7":{},"c_ResultInfo_7_Header":{},"c_ResultInfo_8":{},"c_ResultInfo_8_Header":{},"c_ResultInfo_9":{},"c_ResultInfo_9_Header":{},"c_ResultInfo_10":{},"c_ResultInfo_10_Header":{},"c_ResultInfo_11":{},"c_ResultInfo_11_Header":{},"c_ResultInfo_12":{},"c_ResultInfo_12_Header":{},"c_ResultInfo_13":{},"c_ResultInfo_13_Header":{},"c_ResultInfo_14":{},"c_ResultInfo_14_Header":{},"c_ResultInfo_15":{},"c_ResultInfo_15_Header":{},"IntermediateResultList":[],"c_ResultNeededForRankList_Header":{},"ResultNeededForRankList":[],"FSK":{}},"CurrentParticipant":{"n_ParticipantType":{},"n_ParticipantID":{},"c_Participant":{},"c_ParticipantShort":{},"c_ParticipantFirstName":{},"c_ParticipantLastName":{},"c_Bib":{},"n_StartOrder":{},"NOC":{"n_ID":{},"n_GeoID":{},"c_Name":{},"c_Short":{}},"TeamMemberList":[],"c_Rank":{},"c_Rank_Header":{},"c_Result":{},"c_Result_Header":{},"c_OverallRank":{},"c_OverallRank_Header":{},"c_OverallResult":{},"c_OverallResult_Header":{},"c_ResultInfo_1":{},"c_ResultInfo_1_Header":{},"c_ResultInfo_2":{},"c_ResultInfo_2_Header":{},"c_ResultInfo_3":{},"c_ResultInfo_3_Header":{},"c_ResultInfo_4":{},"c_ResultInfo_4_Header":{},"c_ResultInfo_5":{},"c_ResultInfo_5_Header":{},"c_ResultInfo_6":{},"c_ResultInfo_6_Header":{},"c_ResultInfo_7":{},"c_ResultInfo_7_Header":{},"c_ResultInfo_8":{},"c_ResultInfo_8_Header":{},"c_ResultInfo_9":{},"c_ResultInfo_9_Header":{},"c_ResultInfo_10":{},"c_ResultInfo_10_Header":{},"c_ResultInfo_11":{},"c_ResultInfo_11_Header":{},"c_ResultInfo_12":{},"c_ResultInfo_12_Header":{},"c_ResultInfo_13":{},"c_ResultInfo_13_Header":{},"c_ResultInfo_14":{},"c_ResultInfo_14_Header":{},"c_ResultInfo_15":{},"c_ResultInfo_15_Header":{},"IntermediateResultList":[],"c_ResultNeededForRankList_Header":{},"ResultNeededForRankList":[],"FSK":{}},"LeadingParticipant":{"n_ParticipantType":{},"n_ParticipantID":{},"c_Participant":{},"c_ParticipantShort":{},"c_ParticipantFirstName":{},"c_ParticipantLastName":{},"c_Bib":{},"n_StartOrder":{},"NOC":{"n_ID":{},"n_GeoID":{},"c_Name":{},"c_Short":{}},"TeamMemberList":[],"c_Rank":{},"c_Rank_Header":{},"c_Result":{},"c_Result_Header":{},"c_OverallRank":{},"c_OverallRank_Header":{},"c_OverallResult":{},"c_OverallResult_Header":{},"c_ResultInfo_1":{},"c_ResultInfo_1_Header":{},"c_ResultInfo_2":{},"c_ResultInfo_2_Header":{},"c_ResultInfo_3":{},"c_ResultInfo_3_Header":{},"c_ResultInfo_4":{},"c_ResultInfo_4_Header":{},"c_ResultInfo_5":{},"c_ResultInfo_5_Header":{},"c_ResultInfo_6":{},"c_ResultInfo_6_Header":{},"c_ResultInfo_7":{},"c_ResultInfo_7_Header":{},"c_ResultInfo_8":{},"c_ResultInfo_8_Header":{},"c_ResultInfo_9":{},"c_ResultInfo_9_Header":{},"c_ResultInfo_10":{},"c_ResultInfo_10_Header":{},"c_ResultInfo_11":{},"c_ResultInfo_11_Header":{},"c_ResultInfo_12":{},"c_ResultInfo_12_Header":{},"c_ResultInfo_13":{},"c_ResultInfo_13_Header":{},"c_ResultInfo_14":{},"c_ResultInfo_14_Header":{},"c_ResultInfo_15":{},"c_ResultInfo_15_Header":{},"IntermediateResultList":[],"c_ResultNeededForRankList_Header":{},"ResultNeededForRankList":[],"FSK":{}},"NextParticipant":{"n_ParticipantType":{},"n_ParticipantID":{},"c_Participant":{},"c_ParticipantShort":{},"c_ParticipantFirstName":{},"c_ParticipantLastName":{},"c_Bib":{},"n_StartOrder":{},"NOC":{"n_ID":{},"n_GeoID":{},"c_Name":{},"c_Short":{}},"TeamMemberList":[]},"Tracker":{"ColumnHeaders":{},"ParticipantList":[]},"IntermediateLeaders":{"ColumnHeaders":{},"IntermediateLeaderList":[]},"Race":{"ColumnHeaders":{},"Race":{}},"H2hRace":{"ColumnHeaders":{},"Race":{}},"H2hCompetition":{"c_Phase":{},"Competitor1":{},"Competitor2":{},"RunList":[]}},"Preview":{"MajorResultsInfo":{},"ParticipantList":[]},"StartList":{"PhaseList":[{"n_PhaseID":1937873,"n_PhaseSortNr":1,"n_PhaseEventTypeID":1,"DateTimes":{"Start":{"c_Local":"2022-02-20T11:00:00","d_Local":"/Date(1645354800000+0000)/","n_Local":20220220,"c_UTC":"2022-02-20T03:00:00","d_UTC":"/Date(1645326000000+0000)/","n_UTC":20220220},"End":{"c_Local":"2022-02-20T12:40:00","d_Local":"/Date(1645360800000+0000)/","n_Local":20220220,"c_UTC":"2022-02-20T04:40:00","d_UTC":"/Date(1645332000000+0000)/","n_UTC":20220220}},"c_Participant_Header":"Name","c_StartListInfo_1_Header":"Bib","ParticipantList":[{"n_ParticipantType":1,"n_ParticipantID":1135218,"c_Participant":"NEPRYAEVA Natalia","c_ParticipantShort":"NEPRYAEVA N","c_ParticipantFirstName":"Natalia","c_ParticipantLastName":"Nepryaeva","c_Bib":"1","n_StartOrder":1,"c_StartListInfo_1":"1","NOC":{"n_ID":23062,"n_GeoID":73035,"c_Name":"ROC","c_Short":"ROC"},"n_BirthDate":19950906,"n_HeightMillimetres":1680,"n_HeightInches":66,"TeamMemberList":[]},{"n_ParticipantType":1,"n_ParticipantID":656055,"c_Participant":"JOHAUG Therese","c_ParticipantShort":"JOHAUG T","c_ParticipantFirstName":"Therese","c_ParticipantLastName":"Johaug","c_Bib":"2","n_StartOrder":2,"c_StartListInfo_1":"2","NOC":{"n_ID":153,"n_GeoID":2221,"c_Name":"Norway","c_Short":"NOR"},"n_BirthDate":19880625,"n_HeightMillimetres":1620,"n_HeightInches":63,"TeamMemberList":[]},{"n_ParticipantType":1,"n_ParticipantID":1232503,"c_Participant":"ANDERSSON Ebba","c_ParticipantShort":"ANDERSSON E","c_ParticipantFirstName":"Ebba","c_ParticipantLastName":"Andersson","c_Bib":"3","n_StartOrder":3,"c_StartListInfo_1":"3","NOC":{"n_ID":154,"n_GeoID":2222,"c_Name":"Sweden","c_Short":"SWE"},"n_BirthDate":19970710,"n_HeightMillimetres":1640,"n_HeightInches":64,"TeamMemberList":[]},{"n_ParticipantType":1,"n_ParticipantID":774305,"c_Participant":"DIGGINS Jessie","c_ParticipantShort":"DIGGINS J","c_ParticipantFirstName":"Jessica","c_ParticipantLastName":"Diggins","c_Bib":"4","n_StartOrder":4,"c_StartListInfo_1":"4","NOC":{"n_ID":5,"n_GeoID":2209,"c_Name":"United States","c_Short":"USA"},"n_BirthDate":19910826,"n_HeightMillimetres":1630,"n_HeightInches":64,"TeamMemberList":[]},{"n_ParticipantType":1,"n_ParticipantID":721248,"c_Participant":"PARMAKOSKI Krista","c_ParticipantShort":"PARMAKOSKI K","c_ParticipantFirstName":"Krista","c_ParticipantLastName":"Pärmäkoski","c_Bib":"5","n_StartOrder":5,"c_StartListInfo_1":"5","NOC":{"n_ID":161,"n_GeoID":2237,"c_Name":"Finland","c_Short":"FIN"},"n_BirthDate":19901212,"n_HeightMillimetres":1600,"n_HeightInches":62,"TeamMemberList":[]},{"n_ParticipantType":1,"n_ParticipantID":703248,"c_Participant":"NISKANEN Kerttu","c_ParticipantShort":"NISKANEN K","c_ParticipantFirstName":"Kerttu","c_ParticipantLastName":"Niskanen","c_Bib":"6","n_StartOrder":6,"c_StartListInfo_1":"6","NOC":{"n_ID":161,"n_GeoID":2237,"c_Name":"Finland","c_Short":"FIN"},"n_BirthDate":19880613,"n_HeightMillimetres":1720,"n_HeightInches":67,"TeamMemberList":[]},{"n_ParticipantType":1,"n_ParticipantID":1635399,"c_Participant":"SORINA Tatiana","c_ParticipantShort":"SORINA T","c_ParticipantFirstName":"Tatiana","c_ParticipantLastName":"Sorina","c_Bib":"7","n_StartOrder":7,"c_StartListInfo_1":"7","NOC":{"n_ID":23062,"n_GeoID":73035,"c_Name":"ROC","c_Short":"ROC"},"n_BirthDate":19940413,"n_HeightMillimetres":1710,"n_HeightInches":67,"TeamMemberList":[]},{"n_ParticipantType":1,"n_ParticipantID":763037,"c_Participant":"BRENNAN Rosie","c_ParticipantShort":"BRENNAN R","c_ParticipantFirstName":"Rosie","c_ParticipantLastName":"Brennan","c_Bib":"8","n_StartOrder":8,"c_StartListInfo_1":"8","NOC":{"n_ID":5,"n_GeoID":2209,"c_Name":"United States","c_Short":"USA"},"n_BirthDate":19881202,"n_HeightMillimetres":1680,"n_HeightInches":66,"TeamMemberList":[]},{"n_ParticipantType":1,"n_ParticipantID":1018377,"c_Participant":"STADLOBER Teresa","c_ParticipantShort":"STADLOBER T","c_ParticipantFirstName":"Teresa","c_ParticipantLastName":"Stadlober","c_Bib":"9","n_StartOrder":9,"c_StartListInfo_1":"9","NOC":{"n_ID":151,"n_GeoID":2219,"c_Name":"Austria","c_Short":"AUT"},"n_BirthDate":19930201,"n_HeightMillimetres":1680,"n_HeightInches":66,"TeamMemberList":[]},{"n_ParticipantType":1,"n_ParticipantID":1240502,"c_Participant":"WENG Tiril Udnes","c_ParticipantShort":"WENG TU","c_ParticipantFirstName":"Tiril Udnes","c_ParticipantLastName":"Weng","c_Bib":"10","n_StartOrder":10,"c_StartListInfo_1":"10","NOC":{"n_ID":153,"n_GeoID":2221,"c_Name":"Norway","c_Short":"NOR"},"n_BirthDate":19960929,"TeamMemberList":[]},{"n_ParticipantType":1,"n_ParticipantID":1018338,"c_Participant":"CARL Victoria","c_ParticipantShort":"CARL V","c_ParticipantFirstName":"Victoria","c_ParticipantLastName":"Carl","c_Bib":"11","n_StartOrder":11,"c_StartListInfo_1":"11","NOC":{"n_ID":2,"n_GeoID":2206,"c_Name":"Germany","c_Short":"GER"},"n_BirthDate":19950731,"n_HeightMillimetres":1780,"n_HeightInches":70,"TeamMemberList":[]},{"n_ParticipantType":1,"n_ParticipantID":1240510,"c_Participant":"CLAUDEL Delphine","c_ParticipantShort":"CLAUDEL D","c_ParticipantFirstName":"Delphine","c_ParticipantLastName":"Claudel","c_Bib":"12","n_StartOrder":12,"c_StartListInfo_1":"12","NOC":{"n_ID":144,"n_GeoID":2202,"c_Name":"France","c_Short":"FRA"},"n_BirthDate":19960323,"n_HeightMillimetres":1680,"n_HeightInches":66,"TeamMemberList":[]},{"n_ParticipantType":1,"n_ParticipantID":840397,"c_Participant":"HAGA Ragnhild","c_ParticipantShort":"HAGA R","c_ParticipantFirstName":"Ragnhild","c_ParticipantLastName":"Haga","c_Bib":"13","n_StartOrder":13,"c_StartListInfo_1":"13","NOC":{"n_ID":153,"n_GeoID":2221,"c_Name":"Norway","c_Short":"NOR"},"n_BirthDate":19910212,"TeamMemberList":[]},{"n_ParticipantType":1,"n_ParticipantID":1074462,"c_Participant":"MATINTALO Johanna","c_ParticipantShort":"MATINTALO J","c_ParticipantFirstName":"Johanna","c_ParticipantLastName":"Matintalo","c_Bib":"14","n_StartOrder":14,"c_StartListInfo_1":"14","NOC":{"n_ID":161,"n_GeoID":2237,"c_Name":"Finland","c_Short":"FIN"},"n_BirthDate":19961211,"n_HeightMillimetres":1770,"n_HeightInches":69,"TeamMemberList":[]},{"n_ParticipantType":1,"n_ParticipantID":607446,"c_Participant":"KALLA Charlotte","c_ParticipantShort":"KALLA C","c_ParticipantFirstName":"Charlotte","c_ParticipantLastName":"Kalla","c_Bib":"15","n_StartOrder":15,"c_StartListInfo_1":"15","NOC":{"n_ID":154,"n_GeoID":2222,"c_Name":"Sweden","c_Short":"SWE"},"n_BirthDate":19870722,"n_HeightMillimetres":1620,"n_HeightInches":63,"TeamMemberList":[]},{"n_ParticipantType":1,"n_ParticipantID":2262036,"c_Participant":"RYGALINA Anastasia","c_ParticipantShort":"RYGALINA A","c_ParticipantFirstName":"Anastasia","c_ParticipantLastName":"Rygalina","c_Bib":"16","n_StartOrder":16,"c_StartListInfo_1":"16","NOC":{"n_ID":23062,"n_GeoID":73035,"c_Name":"ROC","c_Short":"ROC"},"n_BirthDate":19960131,"TeamMemberList":[]},{"n_ParticipantType":1,"n_ParticipantID":1240371,"c_Participant":"WENG Lotta Udnes","c_ParticipantShort":"WENG LU","c_ParticipantFirstName":"Lotta Udnes","c_ParticipantLastName":"Weng","c_Bib":"17","n_StartOrder":17,"c_StartListInfo_1":"17","NOC":{"n_ID":153,"n_GeoID":2221,"c_Name":"Norway","c_Short":"NOR"},"n_BirthDate":19960929,"TeamMemberList":[]},{"n_ParticipantType":1,"n_ParticipantID":703249,"c_Participant":"KYLLOENEN Anne","c_ParticipantShort":"KYLLOENEN A","c_ParticipantFirstName":"Anne","c_ParticipantLastName":"Kyllönen","c_Bib":"18","n_StartOrder":18,"c_StartListInfo_1":"18","NOC":{"n_ID":161,"n_GeoID":2237,"c_Name":"Finland","c_Short":"FIN"},"n_BirthDate":19871130,"n_HeightMillimetres":1730,"n_HeightInches":68,"TeamMemberList":[]},{"n_ParticipantType":1,"n_ParticipantID":1635403,"c_Participant":"FINK Pia","c_ParticipantShort":"FINK P","c_ParticipantFirstName":"Pia","c_ParticipantLastName":"Fink","c_Bib":"19","n_StartOrder":19,"c_StartListInfo_1":"19","NOC":{"n_ID":2,"n_GeoID":2206,"c_Name":"Germany","c_Short":"GER"},"n_BirthDate":19950710,"n_HeightMillimetres":1670,"n_HeightInches":65,"TeamMemberList":[]},{"n_ParticipantType":1,"n_ParticipantID":1018286,"c_Participant":"SUNDLING Jonna","c_ParticipantShort":"SUNDLING J","c_ParticipantFirstName":"Jonna","c_ParticipantLastName":"Sundling","c_Bib":"20","n_StartOrder":20,"c_StartListInfo_1":"20","NOC":{"n_ID":154,"n_GeoID":2222,"c_Name":"Sweden","c_Short":"SWE"},"n_BirthDate":19941228,"n_HeightMillimetres":1650,"n_HeightInches":64,"TeamMemberList":[]},{"n_ParticipantType":1,"n_ParticipantID":1356899,"c_Participant":"RIBOM Emma","c_ParticipantShort":"RIBOM E","c_ParticipantFirstName":"Emma","c_ParticipantLastName":"Ribom","c_Bib":"21","n_StartOrder":21,"c_StartListInfo_1":"21","NOC":{"n_ID":154,"n_GeoID":2222,"c_Name":"Sweden","c_Short":"SWE"},"n_BirthDate":19971129,"n_HeightMillimetres":1720,"n_HeightInches":67,"TeamMemberList":[]},{"n_ParticipantType":1,"n_ParticipantID":1135223,"c_Participant":"STEWART-JONES Katherine","c_ParticipantShort":"STEWART-JONES K","c_ParticipantFirstName":"Katherine","c_ParticipantLastName":"Stewart-Jones","c_Bib":"22","n_StartOrder":22,"c_StartListInfo_1":"22","NOC":{"n_ID":159,"n_GeoID":2231,"c_Name":"Canada","c_Short":"CAN"},"n_BirthDate":19950505,"n_HeightMillimetres":1610,"n_HeightInches":63,"TeamMemberList":[]},{"n_ParticipantType":1,"n_ParticipantID":1625481,"c_Participant":"ISTOMINA Mariya","c_ParticipantShort":"ISTOMINA M","c_ParticipantFirstName":"Mariya","c_ParticipantLastName":"Istomina","c_Bib":"23","n_StartOrder":23,"c_StartListInfo_1":"23","NOC":{"n_ID":23062,"n_GeoID":73035,"c_Name":"ROC","c_Short":"ROC"},"n_BirthDate":19970320,"TeamMemberList":[]},{"n_ParticipantType":1,"n_ParticipantID":396503,"c_Participant":"ISHIDA Masako","c_ParticipantShort":"ISHIDA M","c_ParticipantFirstName":"Masako","c_ParticipantLastName":"Ishida","c_Bib":"24","n_StartOrder":24,"c_StartListInfo_1":"24","NOC":{"n_ID":18,"n_GeoID":2241,"c_Name":"Japan","c_Short":"JPN"},"n_BirthDate":19801105,"n_HeightMillimetres":1620,"n_HeightInches":63,"TeamMemberList":[]},{"n_ParticipantType":1,"n_ParticipantID":1477960,"c_Participant":"BENTZ Coralie","c_ParticipantShort":"BENTZ C","c_ParticipantFirstName":"Coralie","c_ParticipantLastName":"Bentz","c_Bib":"25","n_StartOrder":25,"c_StartListInfo_1":"25","NOC":{"n_ID":144,"n_GeoID":2202,"c_Name":"France","c_Short":"FRA"},"n_BirthDate":19960521,"n_HeightMillimetres":1580,"n_HeightInches":62,"TeamMemberList":[]},{"n_ParticipantType":1,"n_ParticipantID":1240886,"c_Participant":"COMARELLA Anna","c_ParticipantShort":"COMARELLA A","c_ParticipantFirstName":"Anna","c_ParticipantLastName":"Comarella","c_Bib":"26","n_StartOrder":26,"c_StartListInfo_1":"26","NOC":{"n_ID":6,"n_GeoID":2210,"c_Name":"Italy","c_Short":"ITA"},"n_BirthDate":19970312,"n_HeightMillimetres":1650,"n_HeightInches":64,"TeamMemberList":[]},{"n_ParticipantType":1,"n_ParticipantID":1231777,"c_Participant":"CHI Chunxue","c_ParticipantShort":"CHI C","c_ParticipantFirstName":"Chunxue","c_ParticipantLastName":"Chi","c_Bib":"27","n_StartOrder":27,"c_StartListInfo_1":"27","NOC":{"n_ID":26,"n_GeoID":2770,"c_Name":"China","c_Short":"CHN"},"n_BirthDate":19980104,"n_HeightMillimetres":1620,"n_HeightInches":63,"TeamMemberList":[]},{"n_ParticipantType":1,"n_ParticipantID":1943158,"c_Participant":"YILAMUJIANG Dinigeer","c_ParticipantShort":"YILAMUJIANG D","c_ParticipantFirstName":"Dinigeer","c_ParticipantLastName":"Yilamujiang","c_Bib":"28","n_StartOrder":28,"c_StartListInfo_1":"28","NOC":{"n_ID":26,"n_GeoID":2770,"c_Name":"China","c_Short":"CHN"},"n_BirthDate":20010503,"TeamMemberList":[]},{"n_ParticipantType":1,"n_ParticipantID":1472997,"c_Participant":"EIDUKA Patricija","c_ParticipantShort":"EIDUKA P","c_ParticipantFirstName":"Patricija","c_ParticipantLastName":"Eiduka","c_Bib":"29","n_StartOrder":29,"c_StartListInfo_1":"29","NOC":{"n_ID":9,"n_GeoID":2218,"c_Name":"Latvia","c_Short":"LAT"},"n_BirthDate":20000201,"n_HeightMillimetres":1600,"n_HeightInches":62,"TeamMemberList":[]},{"n_ParticipantType":1,"n_ParticipantID":1718981,"c_Participant":"MARCISZ Izabela","c_ParticipantShort":"MARCISZ I","c_ParticipantFirstName":"Izabela","c_ParticipantLastName":"Marcisz","c_Bib":"30","n_StartOrder":30,"c_StartListInfo_1":"30","NOC":{"n_ID":150,"n_GeoID":2214,"c_Name":"Poland","c_Short":"POL"},"n_BirthDate":20000518,"TeamMemberList":[]},{"n_ParticipantType":1,"n_ParticipantID":1131331,"c_Participant":"NOVAKOVA Petra","c_ParticipantShort":"NOVAKOVA P","c_ParticipantFirstName":"Petra","c_ParticipantLastName":"Nováková","c_Bib":"31","n_StartOrder":31,"c_StartListInfo_1":"31","NOC":{"n_ID":17,"n_GeoID":2240,"c_Name":"Czech Republic","c_Short":"CZE"},"n_BirthDate":19930817,"n_HeightMillimetres":1630,"n_HeightInches":64,"TeamMemberList":[]},{"n_ParticipantType":1,"n_ParticipantID":1240737,"c_Participant":"HIERNICKEL Lydia","c_ParticipantShort":"HIERNICKEL L","c_ParticipantFirstName":"Lydia","c_ParticipantLastName":"Hiernickel","c_Bib":"32","n_StartOrder":32,"c_StartListInfo_1":"32","NOC":{"n_ID":149,"n_GeoID":2213,"c_Name":"Switzerland","c_Short":"SUI"},"n_BirthDate":19961223,"n_HeightMillimetres":1700,"n_HeightInches":66,"TeamMemberList":[]},{"n_ParticipantType":1,"n_ParticipantID":1018253,"c_Participant":"BEATTY Dahria","c_ParticipantShort":"BEATTY D","c_ParticipantFirstName":"Dahria","c_ParticipantLastName":"Beatty","c_Bib":"33","n_StartOrder":33,"c_StartListInfo_1":"33","NOC":{"n_ID":159,"n_GeoID":2231,"c_Name":"Canada","c_Short":"CAN"},"n_BirthDate":19940307,"n_HeightMillimetres":1810,"n_HeightInches":71,"TeamMemberList":[]},{"n_ParticipantType":1,"n_ParticipantID":1240503,"c_Participant":"FRAEBEL Antonia","c_ParticipantShort":"FRAEBEL A","c_ParticipantFirstName":"Antonia","c_ParticipantLastName":"Fräbel","c_Bib":"34","n_StartOrder":34,"c_StartListInfo_1":"34","NOC":{"n_ID":2,"n_GeoID":2206,"c_Name":"Germany","c_Short":"GER"},"n_BirthDate":19970125,"n_HeightMillimetres":1600,"n_HeightInches":62,"TeamMemberList":[]},{"n_ParticipantType":1,"n_ParticipantID":1947824,"c_Participant":"JIALIN Bayani","c_ParticipantShort":"JIALIN B","c_ParticipantFirstName":"Bayani","c_ParticipantLastName":"Jialin","c_Bib":"35","n_StartOrder":35,"c_StartListInfo_1":"35","NOC":{"n_ID":26,"n_GeoID":2770,"c_Name":"China","c_Short":"CHN"},"n_BirthDate":19991217,"TeamMemberList":[]},{"n_ParticipantType":1,"n_ParticipantID":1352021,"c_Participant":"JANATOVA Katerina","c_ParticipantShort":"JANATOVA K","c_ParticipantFirstName":"Katerina","c_ParticipantLastName":"Janatová","c_Bib":"36","n_StartOrder":36,"c_StartListInfo_1":"36","NOC":{"n_ID":17,"n_GeoID":2240,"c_Name":"Czech Republic","c_Short":"CZE"},"n_BirthDate":19970313,"n_HeightMillimetres":1650,"n_HeightInches":64,"TeamMemberList":[]},{"n_ParticipantType":1,"n_ParticipantID":2079826,"c_Participant":"LAUKLI Sophia","c_ParticipantShort":"LAUKLI S","c_ParticipantFirstName":"Sophia","c_ParticipantLastName":"Laukli","c_Bib":"37","n_StartOrder":37,"c_StartListInfo_1":"37","NOC":{"n_ID":5,"n_GeoID":2209,"c_Name":"United States","c_Short":"USA"},"n_BirthDate":20000608,"TeamMemberList":[]},{"n_ParticipantType":1,"n_ParticipantID":1569093,"c_Participant":"DOLCI Flora","c_ParticipantShort":"DOLCI F","c_ParticipantFirstName":"Flora","c_ParticipantLastName":"Dolci","c_Bib":"38","n_StartOrder":38,"c_StartListInfo_1":"38","NOC":{"n_ID":144,"n_GeoID":2202,"c_Name":"France","c_Short":"FRA"},"n_BirthDate":19991009,"n_HeightMillimetres":1590,"n_HeightInches":62,"TeamMemberList":[]},{"n_ParticipantType":1,"n_ParticipantID":1947848,"c_Participant":"MCCABE Novie","c_ParticipantShort":"MCCABE N","c_ParticipantFirstName":"Novie","c_ParticipantLastName":"McCabe","c_Bib":"39","n_StartOrder":39,"c_StartListInfo_1":"39","NOC":{"n_ID":5,"n_GeoID":2209,"c_Name":"United States","c_Short":"USA"},"n_BirthDate":20011215,"TeamMemberList":[]},{"n_ParticipantType":1,"n_ParticipantID":657143,"c_Participant":"LI Xin","c_ParticipantShort":"LI X","c_ParticipantFirstName":"Xin","c_ParticipantLastName":"Li","c_Bib":"40","n_StartOrder":40,"c_StartListInfo_1":"40","NOC":{"n_ID":26,"n_GeoID":2770,"c_Name":"China","c_Short":"CHN"},"n_BirthDate":19920731,"n_HeightMillimetres":1700,"n_HeightInches":66,"TeamMemberList":[]},{"n_ParticipantType":1,"n_ParticipantID":2180285,"c_Participant":"TSUCHIYA Masae","c_ParticipantShort":"TSUCHIYA M","c_ParticipantFirstName":"Masae","c_ParticipantLastName":"Tsuchiya","c_Bib":"41","n_StartOrder":41,"c_StartListInfo_1":"41","NOC":{"n_ID":18,"n_GeoID":2241,"c_Name":"Japan","c_Short":"JPN"},"n_BirthDate":19961213,"TeamMemberList":[]},{"n_ParticipantType":1,"n_ParticipantID":1123824,"c_Participant":"BROWNE Cendrine","c_ParticipantShort":"BROWNE C","c_ParticipantFirstName":"Cendrine","c_ParticipantLastName":"Browne","c_Bib":"42","n_StartOrder":42,"c_StartListInfo_1":"42","NOC":{"n_ID":159,"n_GeoID":2231,"c_Name":"Canada","c_Short":"CAN"},"n_BirthDate":19930908,"n_HeightMillimetres":1630,"n_HeightInches":64,"TeamMemberList":[]},{"n_ParticipantType":1,"n_ParticipantID":1477974,"c_Participant":"KODAMA Miki","c_ParticipantShort":"KODAMA M","c_ParticipantFirstName":"Miki","c_ParticipantLastName":"Kodama","c_Bib":"43","n_StartOrder":43,"c_StartListInfo_1":"43","NOC":{"n_ID":18,"n_GeoID":2241,"c_Name":"Japan","c_Short":"JPN"},"n_BirthDate":19961121,"n_HeightMillimetres":1490,"n_HeightInches":58,"TeamMemberList":[]},{"n_ParticipantType":1,"n_ParticipantID":603457,"c_Participant":"ANTSYBOR Maryna","c_ParticipantShort":"ANTSYBOR M","c_ParticipantFirstName":"Maryna","c_ParticipantLastName":"Antsybor","c_Bib":"44","n_StartOrder":44,"c_StartListInfo_1":"44","NOC":{"n_ID":13,"n_GeoID":2232,"c_Name":"Ukraine","c_Short":"UKR"},"n_BirthDate":19871010,"n_HeightMillimetres":1610,"n_HeightInches":63,"TeamMemberList":[]},{"n_ParticipantType":1,"n_ParticipantID":1351753,"c_Participant":"PITTIN Cristina","c_ParticipantShort":"PITTIN C","c_ParticipantFirstName":"Cristina","c_ParticipantLastName":"Pittin","c_Bib":"45","n_StartOrder":45,"c_StartListInfo_1":"45","NOC":{"n_ID":6,"n_GeoID":2210,"c_Name":"Italy","c_Short":"ITA"},"n_BirthDate":19981014,"TeamMemberList":[]},{"n_ParticipantType":1,"n_ParticipantID":1240738,"c_Participant":"GANZ Caterina","c_ParticipantShort":"GANZ C","c_ParticipantFirstName":"Caterina","c_ParticipantLastName":"Ganz","c_Bib":"46","n_StartOrder":46,"c_StartListInfo_1":"46","NOC":{"n_ID":6,"n_GeoID":2210,"c_Name":"Italy","c_Short":"ITA"},"n_BirthDate":19951113,"TeamMemberList":[]},{"n_ParticipantType":1,"n_ParticipantID":2079824,"c_Participant":"DI CENTA Martina","c_ParticipantShort":"DI CENTA M","c_ParticipantFirstName":"Martina","c_ParticipantLastName":"Di Centa","c_Bib":"47","n_StartOrder":47,"c_StartListInfo_1":"47","NOC":{"n_ID":6,"n_GeoID":2210,"c_Name":"Italy","c_Short":"ITA"},"n_BirthDate":20000306,"TeamMemberList":[]},{"n_ParticipantType":1,"n_ParticipantID":1625458,"c_Participant":"KOBAYASHI Chika","c_ParticipantShort":"KOBAYASHI C","c_ParticipantFirstName":"Chika","c_ParticipantLastName":"Kobayashi","c_Bib":"48","n_StartOrder":48,"c_StartListInfo_1":"48","NOC":{"n_ID":18,"n_GeoID":2241,"c_Name":"Japan","c_Short":"JPN"},"n_BirthDate":19980703,"n_HeightMillimetres":1560,"n_HeightInches":61,"TeamMemberList":[]},{"n_ParticipantType":1,"n_ParticipantID":1023378,"c_Participant":"HYNCICOVA Petra","c_ParticipantShort":"HYNCICOVA P","c_ParticipantFirstName":"Petra","c_ParticipantLastName":"Hyncicová","c_Bib":"49","n_StartOrder":49,"c_StartListInfo_1":"49","NOC":{"n_ID":17,"n_GeoID":2240,"c_Name":"Czech Republic","c_Short":"CZE"},"n_BirthDate":19940501,"n_HeightMillimetres":1630,"n_HeightInches":64,"TeamMemberList":[]},{"n_ParticipantType":1,"n_ParticipantID":1018240,"c_Participant":"SHURYGA Angelina","c_ParticipantShort":"SHURYGA A","c_ParticipantFirstName":"Angelina","c_ParticipantLastName":"Shuryga","c_Bib":"50","n_StartOrder":50,"c_StartListInfo_1":"50","NOC":{"n_ID":160,"n_GeoID":2236,"c_Name":"Kazakhstan","c_Short":"KAZ"},"n_BirthDate":19961105,"n_HeightMillimetres":1810,"n_HeightInches":71,"TeamMemberList":[]},{"n_ParticipantType":1,"n_ParticipantID":1457141,"c_Participant":"BYKOVA Irina","c_ParticipantShort":"BYKOVA I","c_ParticipantFirstName":"Irina","c_ParticipantLastName":"Bykova","c_Bib":"51","n_StartOrder":51,"c_StartListInfo_1":"51","NOC":{"n_ID":160,"n_GeoID":2236,"c_Name":"Kazakhstan","c_Short":"KAZ"},"n_BirthDate":19930706,"n_HeightMillimetres":1660,"n_HeightInches":65,"TeamMemberList":[]},{"n_ParticipantType":1,"n_ParticipantID":1361495,"c_Participant":"YEATON Jessica","c_ParticipantShort":"YEATON J","c_ParticipantFirstName":"Jessica","c_ParticipantLastName":"Yeaton","c_Bib":"52","n_StartOrder":52,"c_StartListInfo_1":"52","NOC":{"n_ID":157,"n_GeoID":2229,"c_Name":"Australia","c_Short":"AUS"},"n_BirthDate":19911121,"n_HeightMillimetres":1670,"n_HeightInches":65,"TeamMemberList":[]},{"n_ParticipantType":1,"n_ParticipantID":1475610,"c_Participant":"VILA Carola","c_ParticipantShort":"VILA C","c_ParticipantFirstName":"Carola","c_ParticipantLastName":"Vila","c_Bib":"53","n_StartOrder":53,"c_StartListInfo_1":"53","NOC":{"n_ID":155,"n_GeoID":2227,"c_Name":"Andorra","c_Short":"AND"},"n_BirthDate":19990119,"TeamMemberList":[]},{"n_ParticipantType":1,"n_ParticipantID":767759,"c_Participant":"MALEC Vedrana","c_ParticipantShort":"MALEC V","c_ParticipantFirstName":"Vedrana","c_ParticipantLastName":"Malec","c_Bib":"54","n_StartOrder":54,"c_StartListInfo_1":"54","NOC":{"n_ID":89,"n_GeoID":4354,"c_Name":"Croatia","c_Short":"CRO"},"n_BirthDate":19900324,"n_HeightMillimetres":1720,"n_HeightInches":67,"TeamMemberList":[]},{"n_ParticipantType":1,"n_ParticipantID":1135581,"c_Participant":"KLEMENCIC Anita","c_ParticipantShort":"KLEMENCIC A","c_ParticipantFirstName":"Anita","c_ParticipantLastName":"Klemencic","c_Bib":"55","n_StartOrder":55,"c_StartListInfo_1":"55","NOC":{"n_ID":30,"n_GeoID":2783,"c_Name":"Slovenia","c_Short":"SLO"},"n_BirthDate":19960108,"TeamMemberList":[]},{"n_ParticipantType":1,"n_ParticipantID":1351849,"c_Participant":"KARALIOVA Hanna","c_ParticipantShort":"KARALIOVA H","c_ParticipantFirstName":"Hanna","c_ParticipantLastName":"Karaliova","c_Bib":"56","n_StartOrder":56,"c_StartListInfo_1":"56","NOC":{"n_ID":103,"n_GeoID":4387,"c_Name":"Belarus","c_Short":"BLR"},"n_BirthDate":19980908,"TeamMemberList":[]},{"n_ParticipantType":1,"n_ParticipantID":1018340,"c_Participant":"OLEKH Viktoriya","c_ParticipantShort":"OLEKH V","c_ParticipantFirstName":"Viktoriya","c_ParticipantLastName":"Olekh","c_Bib":"57","n_StartOrder":57,"c_StartListInfo_1":"57","NOC":{"n_ID":13,"n_GeoID":2232,"c_Name":"Ukraine","c_Short":"UKR"},"n_BirthDate":19931002,"TeamMemberList":[]},{"n_ParticipantType":1,"n_ParticipantID":2175980,"c_Participant":"STEPASHKINA Nadezhda","c_ParticipantShort":"STEPASHKINA N","c_ParticipantFirstName":"Nadezhda","c_ParticipantLastName":"Stepashkina","c_Bib":"58","n_StartOrder":58,"c_StartListInfo_1":"58","NOC":{"n_ID":160,"n_GeoID":2236,"c_Name":"Kazakhstan","c_Short":"KAZ"},"n_BirthDate":19980904,"TeamMemberList":[]},{"n_ParticipantType":1,"n_ParticipantID":760083,"c_Participant":"NTANOU Maria","c_ParticipantShort":"NTANOU M","c_ParticipantFirstName":"Maria","c_ParticipantLastName":"Ntanou","c_Bib":"59","n_StartOrder":59,"c_StartListInfo_1":"59","NOC":{"n_ID":171,"n_GeoID":2774,"c_Name":"Greece","c_Short":"GRE"},"n_BirthDate":19900303,"n_HeightMillimetres":1680,"n_HeightInches":66,"TeamMemberList":[]},{"n_ParticipantType":1,"n_ParticipantID":823185,"c_Participant":"BENDIKA Baiba","c_ParticipantShort":"BENDIKA B","c_ParticipantFirstName":"Baiba","c_ParticipantLastName":"Bendika","c_Bib":"60","n_StartOrder":60,"c_StartListInfo_1":"60","NOC":{"n_ID":9,"n_GeoID":2218,"c_Name":"Latvia","c_Short":"LAT"},"n_BirthDate":19910627,"n_HeightMillimetres":1560,"n_HeightInches":61,"TeamMemberList":[]},{"n_ParticipantType":1,"n_ParticipantID":1947844,"c_Participant":"KOBIELUSZ Magdalena","c_ParticipantShort":"KOBIELUSZ M","c_ParticipantFirstName":"Magdalena","c_ParticipantLastName":"Kobielusz","c_Bib":"61","n_StartOrder":61,"c_StartListInfo_1":"61","NOC":{"n_ID":150,"n_GeoID":2214,"c_Name":"Poland","c_Short":"POL"},"n_BirthDate":20000908,"TeamMemberList":[]},{"n_ParticipantType":1,"n_ParticipantID":1629764,"c_Participant":"ZERJAV Neza","c_ParticipantShort":"ZERJAV N","c_ParticipantFirstName":"Neža","c_ParticipantLastName":"Žerjav","c_Bib":"62","n_StartOrder":62,"c_StartListInfo_1":"62","NOC":{"n_ID":30,"n_GeoID":2783,"c_Name":"Slovenia","c_Short":"SLO"},"n_BirthDate":19990809,"TeamMemberList":[]},{"n_ParticipantType":1,"n_ParticipantID":1137074,"c_Participant":"KUSMUK Sanja","c_ParticipantShort":"KUSMUK S","c_ParticipantFirstName":"Sanja","c_ParticipantLastName":"Kusmuk","c_Bib":"63","n_StartOrder":63,"c_StartListInfo_1":"63","NOC":{"n_ID":78,"n_GeoID":4324,"c_Name":"Bosnia and Herzegovina","c_Short":"BIH"},"n_BirthDate":19960317,"n_HeightMillimetres":1750,"n_HeightInches":68,"TeamMemberList":[]},{"n_ParticipantType":1,"n_ParticipantID":1484749,"c_Participant":"LECLAIR Laura","c_ParticipantShort":"LECLAIR L","c_ParticipantFirstName":"Laura","c_ParticipantLastName":"Leclair","c_Bib":"64","n_StartOrder":64,"c_StartListInfo_1":"64","NOC":{"n_ID":159,"n_GeoID":2231,"c_Name":"Canada","c_Short":"CAN"},"n_BirthDate":19970115,"TeamMemberList":[]},{"n_ParticipantType":1,"n_ParticipantID":1135234,"c_Participant":"WRIGHT Casey","c_ParticipantShort":"WRIGHT C","c_ParticipantFirstName":"Casey","c_ParticipantLastName":"Wright","c_Bib":"65","n_StartOrder":65,"c_StartListInfo_1":"65","NOC":{"n_ID":157,"n_GeoID":2229,"c_Name":"Australia","c_Short":"AUS"},"n_BirthDate":19941219,"n_HeightMillimetres":1740,"n_HeightInches":68,"TeamMemberList":[]}]}]},"Result":{"IntermediatePhaseList":[{"n_PhaseID":2499551,"c_Phase":"1.3","n_PhaseNr":1,"n_ParticipantsFinished":63,"b_Selected":false,"c_ODF_Pos":"1"},{"n_PhaseID":2499552,"c_Phase":"2.9","n_PhaseNr":2,"n_ParticipantsFinished":63,"b_Selected":false,"c_ODF_Pos":"2"},{"n_PhaseID":2499553,"c_Phase":"6.2","n_PhaseNr":3,"n_ParticipantsFinished":62,"b_Selected":false,"c_ODF_Pos":"3"},{"n_PhaseID":2499554,"c_Phase":"7.5","n_PhaseNr":4,"n_ParticipantsFinished":62,"b_Selected":false,"c_ODF_Pos":"4"},{"n_PhaseID":2499555,"c_Phase":"8.8","n_PhaseNr":5,"n_ParticipantsFinished":62,"b_Selected":false,"c_ODF_Pos":"5"},{"n_PhaseID":2499556,"c_Phase":"10.4","n_PhaseNr":6,"n_ParticipantsFinished":62,"b_Selected":false,"c_ODF_Pos":"6"},{"n_PhaseID":2499557,"c_Phase":"13.7","n_PhaseNr":7,"n_ParticipantsFinished":61,"b_Selected":false,"c_ODF_Pos":"7"},{"n_PhaseID":2499558,"c_Phase":"15.0","n_PhaseNr":8,"n_ParticipantsFinished":61,"b_Selected":false,"c_ODF_Pos":"8"},{"n_PhaseID":2499559,"c_Phase":"16.3","n_PhaseNr":9,"n_ParticipantsFinished":61,"b_Selected":false,"c_ODF_Pos":"9"},{"n_PhaseID":2499560,"c_Phase":"17.9","n_PhaseNr":10,"n_ParticipantsFinished":61,"b_Selected":false,"c_ODF_Pos":"10"},{"n_PhaseID":2499561,"c_Phase":"21.2","n_PhaseNr":11,"n_ParticipantsFinished":60,"b_Selected":false,"c_ODF_Pos":"11"},{"n_PhaseID":2499562,"c_Phase":"22.5","n_PhaseNr":12,"n_ParticipantsFinished":60,"b_Selected":false,"c_ODF_Pos":"12"},{"n_PhaseID":2499563,"c_Phase":"23.8","n_PhaseNr":13,"n_ParticipantsFinished":60,"b_Selected":false,"c_ODF_Pos":"13"},{"n_PhaseID":2499564,"c_Phase":"25.4","n_PhaseNr":14,"n_ParticipantsFinished":60,"b_Selected":false,"c_ODF_Pos":"14"},{"n_PhaseID":2499565,"c_Phase":"28.7","n_PhaseNr":15,"n_ParticipantsFinished":60,"b_Selected":false,"c_ODF_Pos":"15"},{"n_PhaseID":2499566,"c_Phase":"30.0","n_PhaseNr":16,"n_ParticipantsFinished":60,"b_Selected":true,"c_ODF_Pos":"F"}],"PhaseList":[{"n_PhaseID":1937873,"n_PhaseEventTypeID":1,"DateTimes":{"Start":{"c_Local":"2022-02-20T11:00:00","d_Local":"/Date(1645354800000+0000)/","n_Local":20220220,"c_UTC":"2022-02-20T03:00:00","d_UTC":"/Date(1645326000000+0000)/","n_UTC":20220220},"End":{"c_Local":"2022-02-20T12:40:00","d_Local":"/Date(1645360800000+0000)/","n_Local":20220220,"c_UTC":"2022-02-20T04:40:00","d_UTC":"/Date(1645332000000+0000)/","n_UTC":20220220}},"c_ScheduleStatus":"Finished","c_ODF_ScheduleStatus":"FINISHED","c_Rank_Header":"Rank","c_Participant_Header":"Name","c_Result_Header":"Time","c_ResultStatus":"Official","c_ODF_ResultStatus":"OFFICIAL","n_BDF_VideoSessionID":1,"ResultPhaseList":[],"ParticipantList":[{"n_ParticipantType":1,"n_ParticipantID":656055,"c_Participant":"JOHAUG Therese","c_ParticipantShort":"JOHAUG T","c_ParticipantFirstName":"Therese","c_ParticipantLastName":"Johaug","c_Bib":"2","n_StartOrder":2,"NOC":{"n_ID":153,"n_GeoID":2221,"c_Name":"Norway","c_Short":"NOR"},"n_Rank":1,"n_RankSort":1,"c_Rank":"1","c_Result":"1:24:54.0","c_ResultAbs":"1:24:54.0","n_TimeAbs":5094000,"n_TimeRel":0,"b_Completed":true,"b_Upcoming":false,"TeamMemberList":[],"PhaseResultList":[]},{"n_ParticipantType":1,"n_ParticipantID":774305,"c_Participant":"DIGGINS Jessie","c_ParticipantShort":"DIGGINS J","c_ParticipantFirstName":"Jessica","c_ParticipantLastName":"Diggins","c_Bib":"4","n_StartOrder":4,"NOC":{"n_ID":5,"n_GeoID":2209,"c_Name":"United States","c_Short":"USA"},"n_Rank":2,"n_RankSort":2,"c_Rank":"2","c_Result":"+1:43.3","c_ResultAbs":"1:26:37.3","n_TimeAbs":5197300,"n_TimeRel":103300,"b_Completed":true,"b_Upcoming":false,"TeamMemberList":[],"PhaseResultList":[]},{"n_ParticipantType":1,"n_ParticipantID":703248,"c_Participant":"NISKANEN Kerttu","c_ParticipantShort":"NISKANEN K","c_ParticipantFirstName":"Kerttu","c_ParticipantLastName":"Niskanen","c_Bib":"6","n_StartOrder":6,"NOC":{"n_ID":161,"n_GeoID":2237,"c_Name":"Finland","c_Short":"FIN"},"n_Rank":3,"n_RankSort":3,"c_Rank":"3","c_Result":"+2:33.3","c_ResultAbs":"1:27:27.3","n_TimeAbs":5247300,"n_TimeRel":153300,"b_Completed":true,"b_Upcoming":false,"TeamMemberList":[],"PhaseResultList":[]},{"n_ParticipantType":1,"n_ParticipantID":1018286,"c_Participant":"SUNDLING Jonna","c_ParticipantShort":"SUNDLING J","c_ParticipantFirstName":"Jonna","c_ParticipantLastName":"Sundling","c_Bib":"20","n_StartOrder":20,"NOC":{"n_ID":154,"n_GeoID":2222,"c_Name":"Sweden","c_Short":"SWE"},"n_Rank":4,"n_RankSort":4,"c_Rank":"4","c_Result":"+2:35.4","c_ResultAbs":"1:27:29.4","n_TimeAbs":5249400,"n_TimeRel":155400,"b_Completed":true,"b_Upcoming":false,"TeamMemberList":[],"PhaseResultList":[]},{"n_ParticipantType":1,"n_ParticipantID":1635399,"c_Participant":"SORINA Tatiana","c_ParticipantShort":"SORINA T","c_ParticipantFirstName":"Tatiana","c_ParticipantLastName":"Sorina","c_Bib":"7","n_StartOrder":7,"NOC":{"n_ID":23062,"n_GeoID":73035,"c_Name":"ROC","c_Short":"ROC"},"n_Rank":5,"n_RankSort":5,"c_Rank":"5","c_Result":"+2:37.2","c_ResultAbs":"1:27:31.2","n_TimeAbs":5251200,"n_TimeRel":157200,"b_Completed":true,"b_Upcoming":false,"TeamMemberList":[],"PhaseResultList":[]},{"n_ParticipantType":1,"n_ParticipantID":763037,"c_Participant":"BRENNAN Rosie","c_ParticipantShort":"BRENNAN R","c_ParticipantFirstName":"Rosie","c_ParticipantLastName":"Brennan","c_Bib":"8","n_StartOrder":8,"NOC":{"n_ID":5,"n_GeoID":2209,"c_Name":"United States","c_Short":"USA"},"n_Rank":6,"n_RankSort":6,"c_Rank":"6","c_Result":"+2:38.7","c_ResultAbs":"1:27:32.7","n_TimeAbs":5252700,"n_TimeRel":158700,"b_Completed":true,"b_Upcoming":false,"TeamMemberList":[],"PhaseResultList":[]},{"n_ParticipantType":1,"n_ParticipantID":1240510,"c_Participant":"CLAUDEL Delphine","c_ParticipantShort":"CLAUDEL D","c_ParticipantFirstName":"Delphine","c_ParticipantLastName":"Claudel","c_Bib":"12","n_StartOrder":12,"NOC":{"n_ID":144,"n_GeoID":2202,"c_Name":"France","c_Short":"FRA"},"n_Rank":7,"n_RankSort":7,"c_Rank":"7","c_Result":"+2:40.0","c_ResultAbs":"1:27:34.0","n_TimeAbs":5254000,"n_TimeRel":160000,"b_Completed":true,"b_Upcoming":false,"TeamMemberList":[],"PhaseResultList":[]},{"n_ParticipantType":1,"n_ParticipantID":1232503,"c_Participant":"ANDERSSON Ebba","c_ParticipantShort":"ANDERSSON E","c_ParticipantFirstName":"Ebba","c_ParticipantLastName":"Andersson","c_Bib":"3","n_StartOrder":3,"NOC":{"n_ID":154,"n_GeoID":2222,"c_Name":"Sweden","c_Short":"SWE"},"n_Rank":8,"n_RankSort":8,"c_Rank":"8","c_Result":"+2:41.5","c_ResultAbs":"1:27:35.5","n_TimeAbs":5255500,"n_TimeRel":161500,"b_Completed":true,"b_Upcoming":false,"TeamMemberList":[],"PhaseResultList":[]},{"n_ParticipantType":1,"n_ParticipantID":1625481,"c_Participant":"ISTOMINA Mariya","c_ParticipantShort":"ISTOMINA M","c_ParticipantFirstName":"Mariya","c_ParticipantLastName":"Istomina","c_Bib":"23","n_StartOrder":23,"NOC":{"n_ID":23062,"n_GeoID":73035,"c_Name":"ROC","c_Short":"ROC"},"n_Rank":9,"n_RankSort":9,"c_Rank":"9","c_Result":"+3:06.1","c_ResultAbs":"1:28:00.1","n_TimeAbs":5280100,"n_TimeRel":186100,"b_Completed":true,"b_Upcoming":false,"TeamMemberList":[],"PhaseResultList":[]},{"n_ParticipantType":1,"n_ParticipantID":721248,"c_Participant":"PARMAKOSKI Krista","c_ParticipantShort":"PARMAKOSKI K","c_ParticipantFirstName":"Krista","c_ParticipantLastName":"Pärmäkoski","c_Bib":"5","n_StartOrder":5,"NOC":{"n_ID":161,"n_GeoID":2237,"c_Name":"Finland","c_Short":"FIN"},"n_Rank":10,"n_RankSort":10,"c_Rank":"10","c_Result":"+3:41.0","c_ResultAbs":"1:28:35.0","n_TimeAbs":5315000,"n_TimeRel":221000,"b_Completed":true,"b_Upcoming":false,"TeamMemberList":[],"PhaseResultList":[]},{"n_ParticipantType":1,"n_ParticipantID":1018377,"c_Participant":"STADLOBER Teresa","c_ParticipantShort":"STADLOBER T","c_ParticipantFirstName":"Teresa","c_ParticipantLastName":"Stadlober","c_Bib":"9","n_StartOrder":9,"NOC":{"n_ID":151,"n_GeoID":2219,"c_Name":"Austria","c_Short":"AUT"},"n_Rank":11,"n_RankSort":11,"c_Rank":"11","c_Result":"+3:42.5","c_ResultAbs":"1:28:36.5","n_TimeAbs":5316500,"n_TimeRel":222500,"b_Completed":true,"b_Upcoming":false,"TeamMemberList":[],"PhaseResultList":[]},{"n_ParticipantType":1,"n_ParticipantID":1018338,"c_Participant":"CARL Victoria","c_ParticipantShort":"CARL V","c_ParticipantFirstName":"Victoria","c_ParticipantLastName":"Carl","c_Bib":"11","n_StartOrder":11,"NOC":{"n_ID":2,"n_GeoID":2206,"c_Name":"Germany","c_Short":"GER"},"n_Rank":12,"n_RankSort":12,"c_Rank":"12","c_Result":"+5:14.4","c_ResultAbs":"1:30:08.4","n_TimeAbs":5408400,"n_TimeRel":314400,"b_Completed":true,"b_Upcoming":false,"TeamMemberList":[],"PhaseResultList":[]},{"n_ParticipantType":1,"n_ParticipantID":1240371,"c_Participant":"WENG Lotta Udnes","c_ParticipantShort":"WENG LU","c_ParticipantFirstName":"Lotta Udnes","c_ParticipantLastName":"Weng","c_Bib":"17","n_StartOrder":17,"NOC":{"n_ID":153,"n_GeoID":2221,"c_Name":"Norway","c_Short":"NOR"},"n_Rank":13,"n_RankSort":13,"c_Rank":"13","c_Result":"+6:20.3","c_ResultAbs":"1:31:14.3","n_TimeAbs":5474300,"n_TimeRel":380300,"b_Completed":true,"b_Upcoming":false,"TeamMemberList":[],"PhaseResultList":[]},{"n_ParticipantType":1,"n_ParticipantID":1240502,"c_Participant":"WENG Tiril Udnes","c_ParticipantShort":"WENG TU","c_ParticipantFirstName":"Tiril Udnes","c_ParticipantLastName":"Weng","c_Bib":"10","n_StartOrder":10,"NOC":{"n_ID":153,"n_GeoID":2221,"c_Name":"Norway","c_Short":"NOR"},"n_Rank":14,"n_RankSort":14,"c_Rank":"14","c_Result":"+6:21.4","c_ResultAbs":"1:31:15.4","n_TimeAbs":5475400,"n_TimeRel":381400,"b_Completed":true,"b_Upcoming":false,"TeamMemberList":[],"PhaseResultList":[]},{"n_ParticipantType":1,"n_ParticipantID":2079826,"c_Participant":"LAUKLI Sophia","c_ParticipantShort":"LAUKLI S","c_ParticipantFirstName":"Sophia","c_ParticipantLastName":"Laukli","c_Bib":"37","n_StartOrder":37,"NOC":{"n_ID":5,"n_GeoID":2209,"c_Name":"United States","c_Short":"USA"},"n_Rank":15,"n_RankSort":15,"c_Rank":"15","c_Result":"+6:27.2","c_ResultAbs":"1:31:21.2","n_TimeAbs":5481200,"n_TimeRel":387200,"b_Completed":true,"b_Upcoming":false,"TeamMemberList":[],"PhaseResultList":[]},{"n_ParticipantType":1,"n_ParticipantID":1123824,"c_Participant":"BROWNE Cendrine","c_ParticipantShort":"BROWNE C","c_ParticipantFirstName":"Cendrine","c_ParticipantLastName":"Browne","c_Bib":"42","n_StartOrder":42,"NOC":{"n_ID":159,"n_GeoID":2231,"c_Name":"Canada","c_Short":"CAN"},"n_Rank":16,"n_RankSort":16,"c_Rank":"16","c_Result":"+6:27.6","c_ResultAbs":"1:31:21.6","n_TimeAbs":5481600,"n_TimeRel":387600,"b_Completed":true,"b_Upcoming":false,"TeamMemberList":[],"PhaseResultList":[]},{"n_ParticipantType":1,"n_ParticipantID":2262036,"c_Participant":"RYGALINA Anastasia","c_ParticipantShort":"RYGALINA A","c_ParticipantFirstName":"Anastasia","c_ParticipantLastName":"Rygalina","c_Bib":"16","n_StartOrder":16,"NOC":{"n_ID":23062,"n_GeoID":73035,"c_Name":"ROC","c_Short":"ROC"},"n_Rank":17,"n_RankSort":17,"c_Rank":"17","c_Result":"+6:28.1","c_ResultAbs":"1:31:22.1","n_TimeAbs":5482100,"n_TimeRel":388100,"b_Completed":true,"b_Upcoming":false,"TeamMemberList":[],"PhaseResultList":[]},{"n_ParticipantType":1,"n_ParticipantID":1947848,"c_Participant":"MCCABE Novie","c_ParticipantShort":"MCCABE N","c_ParticipantFirstName":"Novie","c_ParticipantLastName":"McCabe","c_Bib":"39","n_StartOrder":39,"NOC":{"n_ID":5,"n_GeoID":2209,"c_Name":"United States","c_Short":"USA"},"n_Rank":18,"n_RankSort":18,"c_Rank":"18","c_Result":"+6:28.5","c_ResultAbs":"1:31:22.5","n_TimeAbs":5482500,"n_TimeRel":388500,"b_Completed":true,"b_Upcoming":false,"TeamMemberList":[],"PhaseResultList":[]},{"n_ParticipantType":1,"n_ParticipantID":1240503,"c_Participant":"FRAEBEL Antonia","c_ParticipantShort":"FRAEBEL A","c_ParticipantFirstName":"Antonia","c_ParticipantLastName":"Fräbel","c_Bib":"34","n_StartOrder":34,"NOC":{"n_ID":2,"n_GeoID":2206,"c_Name":"Germany","c_Short":"GER"},"n_Rank":19,"n_RankSort":19,"c_Rank":"19","c_Result":"+6:29.6","c_ResultAbs":"1:31:23.6","n_TimeAbs":5483600,"n_TimeRel":389600,"b_Completed":true,"b_Upcoming":false,"TeamMemberList":[],"PhaseResultList":[]},{"n_ParticipantType":1,"n_ParticipantID":703249,"c_Participant":"KYLLOENEN Anne","c_ParticipantShort":"KYLLOENEN A","c_ParticipantFirstName":"Anne","c_ParticipantLastName":"Kyllönen","c_Bib":"18","n_StartOrder":18,"NOC":{"n_ID":161,"n_GeoID":2237,"c_Name":"Finland","c_Short":"FIN"},"n_Rank":20,"n_RankSort":20,"c_Rank":"20","c_Result":"+6:47.0","c_ResultAbs":"1:31:41.0","n_TimeAbs":5501000,"n_TimeRel":407000,"b_Completed":true,"b_Upcoming":false,"TeamMemberList":[],"PhaseResultList":[]},{"n_ParticipantType":1,"n_ParticipantID":1718981,"c_Participant":"MARCISZ Izabela","c_ParticipantShort":"MARCISZ I","c_ParticipantFirstName":"Izabela","c_ParticipantLastName":"Marcisz","c_Bib":"30","n_StartOrder":30,"NOC":{"n_ID":150,"n_GeoID":2214,"c_Name":"Poland","c_Short":"POL"},"n_Rank":21,"n_RankSort":21,"c_Rank":"21","c_Result":"+6:49.0","c_ResultAbs":"1:31:43.0","n_TimeAbs":5503000,"n_TimeRel":409000,"b_Completed":true,"b_Upcoming":false,"TeamMemberList":[],"PhaseResultList":[]},{"n_ParticipantType":1,"n_ParticipantID":1352021,"c_Participant":"JANATOVA Katerina","c_ParticipantShort":"JANATOVA K","c_ParticipantFirstName":"Katerina","c_ParticipantLastName":"Janatová","c_Bib":"36","n_StartOrder":36,"NOC":{"n_ID":17,"n_GeoID":2240,"c_Name":"Czech Republic","c_Short":"CZE"},"n_Rank":22,"n_RankSort":22,"c_Rank":"22","c_Result":"+6:49.2","c_ResultAbs":"1:31:43.2","n_TimeAbs":5503200,"n_TimeRel":409200,"b_Completed":true,"b_Upcoming":false,"TeamMemberList":[],"PhaseResultList":[]},{"n_ParticipantType":1,"n_ParticipantID":1074462,"c_Participant":"MATINTALO Johanna","c_ParticipantShort":"MATINTALO J","c_ParticipantFirstName":"Johanna","c_ParticipantLastName":"Matintalo","c_Bib":"14","n_StartOrder":14,"NOC":{"n_ID":161,"n_GeoID":2237,"c_Name":"Finland","c_Short":"FIN"},"n_Rank":23,"n_RankSort":23,"c_Rank":"23","c_Result":"+7:07.7","c_ResultAbs":"1:32:01.7","n_TimeAbs":5521700,"n_TimeRel":427700,"b_Completed":true,"b_Upcoming":false,"TeamMemberList":[],"PhaseResultList":[]},{"n_ParticipantType":1,"n_ParticipantID":1569093,"c_Participant":"DOLCI Flora","c_ParticipantShort":"DOLCI F","c_ParticipantFirstName":"Flora","c_ParticipantLastName":"Dolci","c_Bib":"38","n_StartOrder":38,"NOC":{"n_ID":144,"n_GeoID":2202,"c_Name":"France","c_Short":"FRA"},"n_Rank":24,"n_RankSort":24,"c_Rank":"24","c_Result":"+7:10.7","c_ResultAbs":"1:32:04.7","n_TimeAbs":5524700,"n_TimeRel":430700,"b_Completed":true,"b_Upcoming":false,"TeamMemberList":[],"PhaseResultList":[]},{"n_ParticipantType":1,"n_ParticipantID":1635403,"c_Participant":"FINK Pia","c_ParticipantShort":"FINK P","c_ParticipantFirstName":"Pia","c_ParticipantLastName":"Fink","c_Bib":"19","n_StartOrder":19,"NOC":{"n_ID":2,"n_GeoID":2206,"c_Name":"Germany","c_Short":"GER"},"n_Rank":25,"n_RankSort":25,"c_Rank":"25","c_Result":"+7:12.3","c_ResultAbs":"1:32:06.3","n_TimeAbs":5526300,"n_TimeRel":432300,"b_Completed":true,"b_Upcoming":false,"TeamMemberList":[],"PhaseResultList":[]},{"n_ParticipantType":1,"n_ParticipantID":396503,"c_Participant":"ISHIDA Masako","c_ParticipantShort":"ISHIDA M","c_ParticipantFirstName":"Masako","c_ParticipantLastName":"Ishida","c_Bib":"24","n_StartOrder":24,"NOC":{"n_ID":18,"n_GeoID":2241,"c_Name":"Japan","c_Short":"JPN"},"n_Rank":26,"n_RankSort":26,"c_Rank":"26","c_Result":"+7:12.3","c_ResultAbs":"1:32:06.3","n_TimeAbs":5526300,"n_TimeRel":432300,"b_Completed":true,"b_Upcoming":false,"TeamMemberList":[],"PhaseResultList":[]},{"n_ParticipantType":1,"n_ParticipantID":1240737,"c_Participant":"HIERNICKEL Lydia","c_ParticipantShort":"HIERNICKEL L","c_ParticipantFirstName":"Lydia","c_ParticipantLastName":"Hiernickel","c_Bib":"32","n_StartOrder":32,"NOC":{"n_ID":149,"n_GeoID":2213,"c_Name":"Switzerland","c_Short":"SUI"},"n_Rank":27,"n_RankSort":27,"c_Rank":"27","c_Result":"+7:18.3","c_ResultAbs":"1:32:12.3","n_TimeAbs":5532300,"n_TimeRel":438300,"b_Completed":true,"b_Upcoming":false,"TeamMemberList":[],"PhaseResultList":[]},{"n_ParticipantType":1,"n_ParticipantID":840397,"c_Participant":"HAGA Ragnhild","c_ParticipantShort":"HAGA R","c_ParticipantFirstName":"Ragnhild","c_ParticipantLastName":"Haga","c_Bib":"13","n_StartOrder":13,"NOC":{"n_ID":153,"n_GeoID":2221,"c_Name":"Norway","c_Short":"NOR"},"n_Rank":28,"n_RankSort":28,"c_Rank":"28","c_Result":"+7:25.9","c_ResultAbs":"1:32:19.9","n_TimeAbs":5539900,"n_TimeRel":445900,"b_Completed":true,"b_Upcoming":false,"TeamMemberList":[],"PhaseResultList":[]},{"n_ParticipantType":1,"n_ParticipantID":1356899,"c_Participant":"RIBOM Emma","c_ParticipantShort":"RIBOM E","c_ParticipantFirstName":"Emma","c_ParticipantLastName":"Ribom","c_Bib":"21","n_StartOrder":21,"NOC":{"n_ID":154,"n_GeoID":2222,"c_Name":"Sweden","c_Short":"SWE"},"n_Rank":29,"n_RankSort":29,"c_Rank":"29","c_Result":"+7:33.8","c_ResultAbs":"1:32:27.8","n_TimeAbs":5547800,"n_TimeRel":453800,"b_Completed":true,"b_Upcoming":false,"TeamMemberList":[],"PhaseResultList":[]},{"n_ParticipantType":1,"n_ParticipantID":1135223,"c_Participant":"STEWART-JONES Katherine","c_ParticipantShort":"STEWART-JONES K","c_ParticipantFirstName":"Katherine","c_ParticipantLastName":"Stewart-Jones","c_Bib":"22","n_StartOrder":22,"NOC":{"n_ID":159,"n_GeoID":2231,"c_Name":"Canada","c_Short":"CAN"},"n_Rank":30,"n_RankSort":30,"c_Rank":"30","c_Result":"+7:39.3","c_ResultAbs":"1:32:33.3","n_TimeAbs":5553300,"n_TimeRel":459300,"b_Completed":true,"b_Upcoming":false,"TeamMemberList":[],"PhaseResultList":[]},{"n_ParticipantType":1,"n_ParticipantID":823185,"c_Participant":"BENDIKA Baiba","c_ParticipantShort":"BENDIKA B","c_ParticipantFirstName":"Baiba","c_ParticipantLastName":"Bendika","c_Bib":"60","n_StartOrder":60,"NOC":{"n_ID":9,"n_GeoID":2218,"c_Name":"Latvia","c_Short":"LAT"},"n_Rank":31,"n_RankSort":31,"c_Rank":"31","c_Result":"+8:43.8","c_ResultAbs":"1:33:37.8","n_TimeAbs":5617800,"n_TimeRel":523800,"b_Completed":true,"b_Upcoming":false,"TeamMemberList":[],"PhaseResultList":[]},{"n_ParticipantType":1,"n_ParticipantID":1472997,"c_Participant":"EIDUKA Patricija","c_ParticipantShort":"EIDUKA P","c_ParticipantFirstName":"Patricija","c_ParticipantLastName":"Eiduka","c_Bib":"29","n_StartOrder":29,"NOC":{"n_ID":9,"n_GeoID":2218,"c_Name":"Latvia","c_Short":"LAT"},"n_Rank":32,"n_RankSort":32,"c_Rank":"32","c_Result":"+8:57.2","c_ResultAbs":"1:33:51.2","n_TimeAbs":5631200,"n_TimeRel":537200,"b_Completed":true,"b_Upcoming":false,"TeamMemberList":[],"PhaseResultList":[]},{"n_ParticipantType":1,"n_ParticipantID":1351753,"c_Participant":"PITTIN Cristina","c_ParticipantShort":"PITTIN C","c_ParticipantFirstName":"Cristina","c_ParticipantLastName":"Pittin","c_Bib":"45","n_StartOrder":45,"NOC":{"n_ID":6,"n_GeoID":2210,"c_Name":"Italy","c_Short":"ITA"},"n_Rank":33,"n_RankSort":33,"c_Rank":"33","c_Result":"+9:00.8","c_ResultAbs":"1:33:54.8","n_TimeAbs":5634800,"n_TimeRel":540800,"b_Completed":true,"b_Upcoming":false,"TeamMemberList":[],"PhaseResultList":[]},{"n_ParticipantType":1,"n_ParticipantID":2079824,"c_Participant":"DI CENTA Martina","c_ParticipantShort":"DI CENTA M","c_ParticipantFirstName":"Martina","c_ParticipantLastName":"Di Centa","c_Bib":"47","n_StartOrder":47,"NOC":{"n_ID":6,"n_GeoID":2210,"c_Name":"Italy","c_Short":"ITA"},"n_Rank":34,"n_RankSort":34,"c_Rank":"34","c_Result":"+9:02.6","c_ResultAbs":"1:33:56.6","n_TimeAbs":5636600,"n_TimeRel":542600,"b_Completed":true,"b_Upcoming":false,"TeamMemberList":[],"PhaseResultList":[]},{"n_ParticipantType":1,"n_ParticipantID":607446,"c_Participant":"KALLA Charlotte","c_ParticipantShort":"KALLA C","c_ParticipantFirstName":"Charlotte","c_ParticipantLastName":"Kalla","c_Bib":"15","n_StartOrder":15,"NOC":{"n_ID":154,"n_GeoID":2222,"c_Name":"Sweden","c_Short":"SWE"},"n_Rank":35,"n_RankSort":35,"c_Rank":"35","c_Result":"+9:51.4","c_ResultAbs":"1:34:45.4","n_TimeAbs":5685400,"n_TimeRel":591400,"b_Completed":true,"b_Upcoming":false,"TeamMemberList":[],"PhaseResultList":[]},{"n_ParticipantType":1,"n_ParticipantID":2180285,"c_Participant":"TSUCHIYA Masae","c_ParticipantShort":"TSUCHIYA M","c_ParticipantFirstName":"Masae","c_ParticipantLastName":"Tsuchiya","c_Bib":"41","n_StartOrder":41,"NOC":{"n_ID":18,"n_GeoID":2241,"c_Name":"Japan","c_Short":"JPN"},"n_Rank":36,"n_RankSort":36,"c_Rank":"36","c_Result":"+9:53.6","c_ResultAbs":"1:34:47.6","n_TimeAbs":5687600,"n_TimeRel":593600,"b_Completed":true,"b_Upcoming":false,"TeamMemberList":[],"PhaseResultList":[]},{"n_ParticipantType":1,"n_ParticipantID":603457,"c_Participant":"ANTSYBOR Maryna","c_ParticipantShort":"ANTSYBOR M","c_ParticipantFirstName":"Maryna","c_ParticipantLastName":"Antsybor","c_Bib":"44","n_StartOrder":44,"NOC":{"n_ID":13,"n_GeoID":2232,"c_Name":"Ukraine","c_Short":"UKR"},"n_Rank":37,"n_RankSort":37,"c_Rank":"37","c_Result":"+10:37.3","c_ResultAbs":"1:35:31.3","n_TimeAbs":5731300,"n_TimeRel":637300,"b_Completed":true,"b_Upcoming":false,"TeamMemberList":[],"PhaseResultList":[]},{"n_ParticipantType":1,"n_ParticipantID":1231777,"c_Participant":"CHI Chunxue","c_ParticipantShort":"CHI C","c_ParticipantFirstName":"Chunxue","c_ParticipantLastName":"Chi","c_Bib":"27","n_StartOrder":27,"NOC":{"n_ID":26,"n_GeoID":2770,"c_Name":"China","c_Short":"CHN"},"n_Rank":38,"n_RankSort":38,"c_Rank":"38","c_Result":"+10:47.0","c_ResultAbs":"1:35:41.0","n_TimeAbs":5741000,"n_TimeRel":647000,"b_Completed":true,"b_Upcoming":false,"TeamMemberList":[],"PhaseResultList":[]},{"n_ParticipantType":1,"n_ParticipantID":1018253,"c_Participant":"BEATTY Dahria","c_ParticipantShort":"BEATTY D","c_ParticipantFirstName":"Dahria","c_ParticipantLastName":"Beatty","c_Bib":"33","n_StartOrder":33,"NOC":{"n_ID":159,"n_GeoID":2231,"c_Name":"Canada","c_Short":"CAN"},"n_Rank":39,"n_RankSort":39,"c_Rank":"39","c_Result":"+11:14.2","c_ResultAbs":"1:36:08.2","n_TimeAbs":5768200,"n_TimeRel":674200,"b_Completed":true,"b_Upcoming":false,"TeamMemberList":[],"PhaseResultList":[]},{"n_ParticipantType":1,"n_ParticipantID":1240886,"c_Participant":"COMARELLA Anna","c_ParticipantShort":"COMARELLA A","c_ParticipantFirstName":"Anna","c_ParticipantLastName":"Comarella","c_Bib":"26","n_StartOrder":26,"NOC":{"n_ID":6,"n_GeoID":2210,"c_Name":"Italy","c_Short":"ITA"},"n_Rank":40,"n_RankSort":40,"c_Rank":"40","c_Result":"+11:18.4","c_ResultAbs":"1:36:12.4","n_TimeAbs":5772400,"n_TimeRel":678400,"b_Completed":true,"b_Upcoming":false,"TeamMemberList":[],"PhaseResultList":[]},{"n_ParticipantType":1,"n_ParticipantID":1023378,"c_Participant":"HYNCICOVA Petra","c_ParticipantShort":"HYNCICOVA P","c_ParticipantFirstName":"Petra","c_ParticipantLastName":"Hyncicová","c_Bib":"49","n_StartOrder":49,"NOC":{"n_ID":17,"n_GeoID":2240,"c_Name":"Czech Republic","c_Short":"CZE"},"n_Rank":41,"n_RankSort":41,"c_Rank":"41","c_Result":"+11:32.6","c_ResultAbs":"1:36:26.6","n_TimeAbs":5786600,"n_TimeRel":692600,"b_Completed":true,"b_Upcoming":false,"TeamMemberList":[],"PhaseResultList":[]},{"n_ParticipantType":1,"n_ParticipantID":1018240,"c_Participant":"SHURYGA Angelina","c_ParticipantShort":"SHURYGA A","c_ParticipantFirstName":"Angelina","c_ParticipantLastName":"Shuryga","c_Bib":"50","n_StartOrder":50,"NOC":{"n_ID":160,"n_GeoID":2236,"c_Name":"Kazakhstan","c_Short":"KAZ"},"n_Rank":42,"n_RankSort":42,"c_Rank":"42","c_Result":"+11:35.6","c_ResultAbs":"1:36:29.6","n_TimeAbs":5789600,"n_TimeRel":695600,"b_Completed":true,"b_Upcoming":false,"TeamMemberList":[],"PhaseResultList":[]},{"n_ParticipantType":1,"n_ParticipantID":1361495,"c_Participant":"YEATON Jessica","c_ParticipantShort":"YEATON J","c_ParticipantFirstName":"Jessica","c_ParticipantLastName":"Yeaton","c_Bib":"52","n_StartOrder":52,"NOC":{"n_ID":157,"n_GeoID":2229,"c_Name":"Australia","c_Short":"AUS"},"n_Rank":43,"n_RankSort":43,"c_Rank":"43","c_Result":"+12:12.1","c_ResultAbs":"1:37:06.1","n_TimeAbs":5826100,"n_TimeRel":732100,"b_Completed":true,"b_Upcoming":false,"TeamMemberList":[],"PhaseResultList":[]},{"n_ParticipantType":1,"n_ParticipantID":1477960,"c_Participant":"BENTZ Coralie","c_ParticipantShort":"BENTZ C","c_ParticipantFirstName":"Coralie","c_ParticipantLastName":"Bentz","c_Bib":"25","n_StartOrder":25,"NOC":{"n_ID":144,"n_GeoID":2202,"c_Name":"France","c_Short":"FRA"},"n_Rank":44,"n_RankSort":44,"c_Rank":"44","c_Result":"+13:14.2","c_ResultAbs":"1:38:08.2","n_TimeAbs":5888200,"n_TimeRel":794200,"b_Completed":true,"b_Upcoming":false,"TeamMemberList":[],"PhaseResultList":[]},{"n_ParticipantType":1,"n_ParticipantID":1240738,"c_Participant":"GANZ Caterina","c_ParticipantShort":"GANZ C","c_ParticipantFirstName":"Caterina","c_ParticipantLastName":"Ganz","c_Bib":"46","n_StartOrder":46,"NOC":{"n_ID":6,"n_GeoID":2210,"c_Name":"Italy","c_Short":"ITA"},"n_Rank":45,"n_RankSort":45,"c_Rank":"45","c_Result":"+13:25.5","c_ResultAbs":"1:38:19.5","n_TimeAbs":5899500,"n_TimeRel":805500,"b_Completed":true,"b_Upcoming":false,"TeamMemberList":[],"PhaseResultList":[]},{"n_ParticipantType":1,"n_ParticipantID":657143,"c_Participant":"LI Xin","c_ParticipantShort":"LI X","c_ParticipantFirstName":"Xin","c_ParticipantLastName":"Li","c_Bib":"40","n_StartOrder":40,"NOC":{"n_ID":26,"n_GeoID":2770,"c_Name":"China","c_Short":"CHN"},"n_Rank":46,"n_RankSort":46,"c_Rank":"46","c_Result":"+13:45.2","c_ResultAbs":"1:38:39.2","n_TimeAbs":5919200,"n_TimeRel":825200,"b_Completed":true,"b_Upcoming":false,"TeamMemberList":[],"PhaseResultList":[]},{"n_ParticipantType":1,"n_ParticipantID":1947824,"c_Participant":"JIALIN Bayani","c_ParticipantShort":"JIALIN B","c_ParticipantFirstName":"Bayani","c_ParticipantLastName":"Jialin","c_Bib":"35","n_StartOrder":35,"NOC":{"n_ID":26,"n_GeoID":2770,"c_Name":"China","c_Short":"CHN"},"n_Rank":47,"n_RankSort":47,"c_Rank":"47","c_Result":"+14:20.8","c_ResultAbs":"1:39:14.8","n_TimeAbs":5954800,"n_TimeRel":860800,"b_Completed":true,"b_Upcoming":false,"TeamMemberList":[],"PhaseResultList":[]},{"n_ParticipantType":1,"n_ParticipantID":1475610,"c_Participant":"VILA Carola","c_ParticipantShort":"VILA C","c_ParticipantFirstName":"Carola","c_ParticipantLastName":"Vila","c_Bib":"53","n_StartOrder":53,"NOC":{"n_ID":155,"n_GeoID":2227,"c_Name":"Andorra","c_Short":"AND"},"n_Rank":48,"n_RankSort":48,"c_Rank":"48","c_Result":"+14:24.1","c_ResultAbs":"1:39:18.1","n_TimeAbs":5958100,"n_TimeRel":864100,"b_Completed":true,"b_Upcoming":false,"TeamMemberList":[],"PhaseResultList":[]},{"n_ParticipantType":1,"n_ParticipantID":2175980,"c_Participant":"STEPASHKINA Nadezhda","c_ParticipantShort":"STEPASHKINA N","c_ParticipantFirstName":"Nadezhda","c_ParticipantLastName":"Stepashkina","c_Bib":"58","n_StartOrder":58,"NOC":{"n_ID":160,"n_GeoID":2236,"c_Name":"Kazakhstan","c_Short":"KAZ"},"n_Rank":49,"n_RankSort":49,"c_Rank":"49","c_Result":"+14:44.8","c_ResultAbs":"1:39:38.8","n_TimeAbs":5978800,"n_TimeRel":884800,"b_Completed":true,"b_Upcoming":false,"TeamMemberList":[],"PhaseResultList":[]},{"n_ParticipantType":1,"n_ParticipantID":1477974,"c_Participant":"KODAMA Miki","c_ParticipantShort":"KODAMA M","c_ParticipantFirstName":"Miki","c_ParticipantLastName":"Kodama","c_Bib":"43","n_StartOrder":43,"NOC":{"n_ID":18,"n_GeoID":2241,"c_Name":"Japan","c_Short":"JPN"},"n_Rank":50,"n_RankSort":50,"c_Rank":"50","c_Result":"+14:59.8","c_ResultAbs":"1:39:53.8","n_TimeAbs":5993800,"n_TimeRel":899800,"b_Completed":true,"b_Upcoming":false,"TeamMemberList":[],"PhaseResultList":[]},{"n_ParticipantType":1,"n_ParticipantID":1484749,"c_Participant":"LECLAIR Laura","c_ParticipantShort":"LECLAIR L","c_ParticipantFirstName":"Laura","c_ParticipantLastName":"Leclair","c_Bib":"64","n_StartOrder":64,"NOC":{"n_ID":159,"n_GeoID":2231,"c_Name":"Canada","c_Short":"CAN"},"n_Rank":51,"n_RankSort":51,"c_Rank":"51","c_Result":"+15:20.5","c_ResultAbs":"1:40:14.5","n_TimeAbs":6014500,"n_TimeRel":920500,"b_Completed":true,"b_Upcoming":false,"TeamMemberList":[],"PhaseResultList":[]},{"n_ParticipantType":1,"n_ParticipantID":767759,"c_Participant":"MALEC Vedrana","c_ParticipantShort":"MALEC V","c_ParticipantFirstName":"Vedrana","c_ParticipantLastName":"Malec","c_Bib":"54","n_StartOrder":54,"NOC":{"n_ID":89,"n_GeoID":4354,"c_Name":"Croatia","c_Short":"CRO"},"n_Rank":52,"n_RankSort":52,"c_Rank":"52","c_Result":"+16:24.6","c_ResultAbs":"1:41:18.6","n_TimeAbs":6078600,"n_TimeRel":984600,"b_Completed":true,"b_Upcoming":false,"TeamMemberList":[],"PhaseResultList":[]},{"n_ParticipantType":1,"n_ParticipantID":1629764,"c_Participant":"ZERJAV Neza","c_ParticipantShort":"ZERJAV N","c_ParticipantFirstName":"Neža","c_ParticipantLastName":"Žerjav","c_Bib":"62","n_StartOrder":62,"NOC":{"n_ID":30,"n_GeoID":2783,"c_Name":"Slovenia","c_Short":"SLO"},"n_Rank":53,"n_RankSort":53,"c_Rank":"53","c_Result":"+17:20.2","c_ResultAbs":"1:42:14.2","n_TimeAbs":6134200,"n_TimeRel":1040200,"b_Completed":true,"b_Upcoming":false,"TeamMemberList":[],"PhaseResultList":[]},{"n_ParticipantType":1,"n_ParticipantID":1457141,"c_Participant":"BYKOVA Irina","c_ParticipantShort":"BYKOVA I","c_ParticipantFirstName":"Irina","c_ParticipantLastName":"Bykova","c_Bib":"51","n_StartOrder":51,"NOC":{"n_ID":160,"n_GeoID":2236,"c_Name":"Kazakhstan","c_Short":"KAZ"},"n_Rank":54,"n_RankSort":54,"c_Rank":"54","c_Result":"+17:48.0","c_ResultAbs":"1:42:42.0","n_TimeAbs":6162000,"n_TimeRel":1068000,"b_Completed":true,"b_Upcoming":false,"TeamMemberList":[],"PhaseResultList":[]},{"n_ParticipantType":1,"n_ParticipantID":1625458,"c_Participant":"KOBAYASHI Chika","c_ParticipantShort":"KOBAYASHI C","c_ParticipantFirstName":"Chika","c_ParticipantLastName":"Kobayashi","c_Bib":"48","n_StartOrder":48,"NOC":{"n_ID":18,"n_GeoID":2241,"c_Name":"Japan","c_Short":"JPN"},"n_Rank":55,"n_RankSort":55,"c_Rank":"55","c_Result":"+18:39.1","c_ResultAbs":"1:43:33.1","n_TimeAbs":6213100,"n_TimeRel":1119100,"b_Completed":true,"b_Upcoming":false,"TeamMemberList":[],"PhaseResultList":[]},{"n_ParticipantType":1,"n_ParticipantID":1135234,"c_Participant":"WRIGHT Casey","c_ParticipantShort":"WRIGHT C","c_ParticipantFirstName":"Casey","c_ParticipantLastName":"Wright","c_Bib":"65","n_StartOrder":65,"NOC":{"n_ID":157,"n_GeoID":2229,"c_Name":"Australia","c_Short":"AUS"},"n_Rank":56,"n_RankSort":56,"c_Rank":"56","c_Result":"+19:25.9","c_ResultAbs":"1:44:19.9","n_TimeAbs":6259900,"n_TimeRel":1165900,"b_Completed":true,"b_Upcoming":false,"TeamMemberList":[],"PhaseResultList":[]},{"n_ParticipantType":1,"n_ParticipantID":1947844,"c_Participant":"KOBIELUSZ Magdalena","c_ParticipantShort":"KOBIELUSZ M","c_ParticipantFirstName":"Magdalena","c_ParticipantLastName":"Kobielusz","c_Bib":"61","n_StartOrder":61,"NOC":{"n_ID":150,"n_GeoID":2214,"c_Name":"Poland","c_Short":"POL"},"n_Rank":57,"n_RankSort":57,"c_Rank":"57","c_Result":"+19:54.8","c_ResultAbs":"1:44:48.8","n_TimeAbs":6288800,"n_TimeRel":1194800,"b_Completed":true,"b_Upcoming":false,"TeamMemberList":[],"PhaseResultList":[]},{"n_ParticipantType":1,"n_ParticipantID":1018340,"c_Participant":"OLEKH Viktoriya","c_ParticipantShort":"OLEKH V","c_ParticipantFirstName":"Viktoriya","c_ParticipantLastName":"Olekh","c_Bib":"57","n_StartOrder":57,"NOC":{"n_ID":13,"n_GeoID":2232,"c_Name":"Ukraine","c_Short":"UKR"},"n_Rank":58,"n_RankSort":58,"c_Rank":"58","c_Result":"+21:28.1","c_ResultAbs":"1:46:22.1","n_TimeAbs":6382100,"n_TimeRel":1288100,"b_Completed":true,"b_Upcoming":false,"TeamMemberList":[],"PhaseResultList":[]},{"n_ParticipantType":1,"n_ParticipantID":1135581,"c_Participant":"KLEMENCIC Anita","c_ParticipantShort":"KLEMENCIC A","c_ParticipantFirstName":"Anita","c_ParticipantLastName":"Klemencic","c_Bib":"55","n_StartOrder":55,"NOC":{"n_ID":30,"n_GeoID":2783,"c_Name":"Slovenia","c_Short":"SLO"},"n_Rank":59,"n_RankSort":59,"c_Rank":"59","c_Result":"+21:43.6","c_ResultAbs":"1:46:37.6","n_TimeAbs":6397600,"n_TimeRel":1303600,"b_Completed":true,"b_Upcoming":false,"TeamMemberList":[],"PhaseResultList":[]},{"n_ParticipantType":1,"n_ParticipantID":1943158,"c_Participant":"YILAMUJIANG Dinigeer","c_ParticipantShort":"YILAMUJIANG D","c_ParticipantFirstName":"Dinigeer","c_ParticipantLastName":"Yilamujiang","c_Bib":"28","n_StartOrder":28,"NOC":{"n_ID":26,"n_GeoID":2770,"c_Name":"China","c_Short":"CHN"},"n_Rank":60,"n_RankSort":60,"c_Rank":"60","c_Result":"+25:10.2","c_ResultAbs":"1:50:04.2","n_TimeAbs":6604200,"n_TimeRel":1510200,"b_Completed":true,"b_Upcoming":false,"TeamMemberList":[],"PhaseResultList":[]},{"n_ParticipantType":1,"n_ParticipantID":760083,"c_Participant":"NTANOU Maria","c_ParticipantShort":"NTANOU M","c_ParticipantFirstName":"Maria","c_ParticipantLastName":"Ntanou","c_Bib":"59","n_StartOrder":59,"NOC":{"n_ID":171,"n_GeoID":2774,"c_Name":"Greece","c_Short":"GRE"},"n_Rank":61,"n_RankSort":61,"c_Rank":"61","c_Result":"LAP","c_ResultAbs":"LAP","b_Completed":true,"b_Upcoming":false,"TeamMemberList":[],"PhaseResultList":[]},{"n_ParticipantType":1,"n_ParticipantID":1135218,"c_Participant":"NEPRYAEVA Natalia","c_ParticipantShort":"NEPRYAEVA N","c_ParticipantFirstName":"Natalia","c_ParticipantLastName":"Nepryaeva","c_Bib":"1","n_StartOrder":1,"NOC":{"n_ID":23062,"n_GeoID":73035,"c_Name":"ROC","c_Short":"ROC"},"n_RankSort":62,"c_Result":"DNF","c_ResultAbs":"DNF","c_ODF_IRM":"DNF","b_Completed":true,"b_Upcoming":false,"TeamMemberList":[],"PhaseResultList":[]},{"n_ParticipantType":1,"n_ParticipantID":1131331,"c_Participant":"NOVAKOVA Petra","c_ParticipantShort":"NOVAKOVA P","c_ParticipantFirstName":"Petra","c_ParticipantLastName":"Nováková","c_Bib":"31","n_StartOrder":31,"NOC":{"n_ID":17,"n_GeoID":2240,"c_Name":"Czech Republic","c_Short":"CZE"},"n_RankSort":63,"c_Result":"DNF","c_ResultAbs":"DNF","c_ODF_IRM":"DNF","b_Completed":true,"b_Upcoming":false,"TeamMemberList":[],"PhaseResultList":[]},{"n_ParticipantType":1,"n_ParticipantID":1351849,"c_Participant":"KARALIOVA Hanna","c_ParticipantShort":"KARALIOVA H","c_ParticipantFirstName":"Hanna","c_ParticipantLastName":"Karaliova","c_Bib":"56","n_StartOrder":56,"NOC":{"n_ID":103,"n_GeoID":4387,"c_Name":"Belarus","c_Short":"BLR"},"n_RankSort":64,"c_Result":"DNS","c_ResultAbs":"DNS","c_ODF_IRM":"DNS","b_Completed":true,"b_Upcoming":false,"TeamMemberList":[],"PhaseResultList":[]},{"n_ParticipantType":1,"n_ParticipantID":1137074,"c_Participant":"KUSMUK Sanja","c_ParticipantShort":"KUSMUK S","c_ParticipantFirstName":"Sanja","c_ParticipantLastName":"Kusmuk","c_Bib":"63","n_StartOrder":63,"NOC":{"n_ID":78,"n_GeoID":4324,"c_Name":"Bosnia and Herzegovina","c_Short":"BIH"},"n_RankSort":65,"c_Result":"DNS","c_ResultAbs":"DNS","c_ODF_IRM":"DNS","b_Completed":true,"b_Upcoming":false,"TeamMemberList":[],"PhaseResultList":[]}]}],"EventPhaseRanking":{}},"Standings":{"Phase":{},"ResultPhaseList":[],"ParticipantList":[]},"Summary":{"Phase":{},"ParticipantList":[]},"Legend":[{"c_Name":"DNF","c_Description":"Did Not Finish"},{"c_Name":"DNS","c_Description":"Did Not Start"},{"c_Name":"DQB","c_Description":"Disqualified For Unsportsmanlike Behavior"},{"c_Name":"DSQ","c_Description":"Disqualified"},{"c_Name":"LAP","c_Description":"Lapped"},{"c_Name":"LL","c_Description":"Lucky Loser"},{"c_Name":"NPS","c_Description":"Not Permitted to Start"},{"c_Name":"Q","c_Description":"Qualified"},{"c_Name":"RAL","c_Description":"Ranked as Last"}]}
