{"PhaseInfo":{"Sport":{"n_ID":[307],"n_TypeID":[3],"c_Name":["Skeleton"],"c_Short":["SKN"]},"Event":{"n_ID":[10776],"n_TypeID":[1],"c_Name":["Individual"],"c_Short":["Individual"],"n_Sort":[4]},"Gender":{"n_ID":[1],"c_Name":["Men"],"c_Short":["M"]},"GenderEvent":{"n_ID":[4345],"c_Name":["Men's Individual"],"c_Short":["Men's Individual"]},"n_CompetitionSetID":[2],"n_SeasonID":[501],"n_Season":[20212022],"n_PhaseID":[2412932],"c_Phase":["Run 3"],"n_PhaseNr":[3],"n_PhaseEventTypeID":[1],"n_EventPhaseID":[1937920],"DateTimes":{"Start":{"c_Local":["2022-02-11T20:20:00"],"d_Local":["/Date(1644610800000+0000)/"],"n_Local":[20220211],"c_UTC":["2022-02-11T12:20:00"],"d_UTC":["/Date(1644582000000+0000)/"],"n_UTC":[20220211]},"End":{"c_Local":["2022-02-11T21:15:00"],"d_Local":["/Date(1644614100000+0000)/"],"n_Local":[20220211],"c_UTC":["2022-02-11T13:15:00"],"d_UTC":["/Date(1644585300000+0000)/"],"n_UTC":[20220211]}},"Venue":{"n_ID":[73852],"c_Name":["Yanqing Sliding Centre"],"c_Short":{}},"Location":{"n_ID":[53887],"c_Name":["Yanqing"],"c_Short":{}},"Country":{"n_ID":[2770],"c_Name":["China"],"c_Short":["CHN"]},"c_ScheduleStatus":["Finished"],"c_ResultStatus":["Official"],"c_ODF_ScheduleStatus":["FINISHED"],"c_ODF_ResultStatus":["OFFICIAL"],"b_Scheduled":[false],"b_StartList":[false],"b_InProgress":[false],"b_Finished":[true],"b_LiveWindow":[false],"b_Delayed":[false],"b_Postponed":[false],"b_Cancelled":[false],"b_Rescheduled":[false],"n_ParticipantsTotal":{},"n_ParticipantsCompleted":{},"CurrentResultPhase":{},"CourseInfoList":[]},"Medals":{"GoldMedals":[],"SilverMedals":[],"BronzeMedals":[]},"Current":{"LastParticipant":{"n_ParticipantType":{},"n_ParticipantID":{},"c_Participant":{},"c_ParticipantShort":{},"c_ParticipantFirstName":{},"c_ParticipantLastName":{},"c_Bib":{},"n_StartOrder":{},"NOC":{"n_ID":{},"n_GeoID":{},"c_Name":{},"c_Short":{}},"TeamMemberList":[],"c_Rank":{},"c_Rank_Header":{},"c_Result":{},"c_Result_Header":{},"c_OverallRank":{},"c_OverallRank_Header":{},"c_OverallResult":{},"c_OverallResult_Header":{},"c_ResultInfo_1":{},"c_ResultInfo_1_Header":{},"c_ResultInfo_2":{},"c_ResultInfo_2_Header":{},"c_ResultInfo_3":{},"c_ResultInfo_3_Header":{},"c_ResultInfo_4":{},"c_ResultInfo_4_Header":{},"c_ResultInfo_5":{},"c_ResultInfo_5_Header":{},"c_ResultInfo_6":{},"c_ResultInfo_6_Header":{},"c_ResultInfo_7":{},"c_ResultInfo_7_Header":{},"c_ResultInfo_8":{},"c_ResultInfo_8_Header":{},"c_ResultInfo_9":{},"c_ResultInfo_9_Header":{},"c_ResultInfo_10":{},"c_ResultInfo_10_Header":{},"c_ResultInfo_11":{},"c_ResultInfo_11_Header":{},"c_ResultInfo_12":{},"c_ResultInfo_12_Header":{},"c_ResultInfo_13":{},"c_ResultInfo_13_Header":{},"c_ResultInfo_14":{},"c_ResultInfo_14_Header":{},"c_ResultInfo_15":{},"c_ResultInfo_15_Header":{},"IntermediateResultList":[{"c_IntermediateFull":"Start","c_Intermediate":"Start","c_IntermediateShort":"Start","c_ODF_Pos":"S"},{"c_IntermediateFull":"1","c_Intermediate":"1","c_IntermediateShort":"1","c_ODF_Pos":"1"},{"c_IntermediateFull":"2","c_Intermediate":"2","c_IntermediateShort":"2","c_ODF_Pos":"2"},{"c_IntermediateFull":"3","c_Intermediate":"3","c_IntermediateShort":"3","c_ODF_Pos":"3"},{"c_IntermediateFull":"4","c_Intermediate":"4","c_IntermediateShort":"4","c_ODF_Pos":"4"},{"c_IntermediateFull":"Finish","c_Intermediate":"Finish","c_IntermediateShort":"Finish","c_ODF_Pos":"F"}],"c_ResultNeededForRankList_Header":{},"ResultNeededForRankList":[],"FSK":{}},"CurrentParticipant":{"n_ParticipantType":[1],"n_ParticipantID":[1125020],"c_Participant":["TIMMINGS Nicholas"],"c_ParticipantShort":["TIMMINGS N"],"c_ParticipantFirstName":["Nicholas"],"c_ParticipantLastName":["Timmings"],"c_Bib":["23"],"n_StartOrder":[25],"NOC":{"n_ID":[157],"n_GeoID":[2229],"c_Name":["Australia"],"c_Short":["AUS"]},"TeamMemberList":[],"c_Rank":["20"],"c_Rank_Header":{},"c_Result":["+1.62"],"c_Result_Header":{},"c_OverallRank":["25"],"c_OverallRank_Header":{},"c_OverallResult":["+7.88"],"c_OverallResult_Header":{},"c_ResultInfo_1":["126.0"],"c_ResultInfo_1_Header":{},"c_ResultInfo_2":{},"c_ResultInfo_2_Header":{},"c_ResultInfo_3":{},"c_ResultInfo_3_Header":{},"c_ResultInfo_4":{},"c_ResultInfo_4_Header":{},"c_ResultInfo_5":{},"c_ResultInfo_5_Header":{},"c_ResultInfo_6":{},"c_ResultInfo_6_Header":{},"c_ResultInfo_7":{},"c_ResultInfo_7_Header":{},"c_ResultInfo_8":{},"c_ResultInfo_8_Header":{},"c_ResultInfo_9":{},"c_ResultInfo_9_Header":{},"c_ResultInfo_10":{},"c_ResultInfo_10_Header":{},"c_ResultInfo_11":{},"c_ResultInfo_11_Header":{},"c_ResultInfo_12":{},"c_ResultInfo_12_Header":{},"c_ResultInfo_13":{},"c_ResultInfo_13_Header":{},"c_ResultInfo_14":{},"c_ResultInfo_14_Header":{},"c_ResultInfo_15":{},"c_ResultInfo_15_Header":{},"IntermediateResultList":[{"c_IntermediateFull":"Start","c_Intermediate":"Start","c_IntermediateShort":"Start","c_ODF_Pos":"S","c_Rank":"25","c_Time":"2:11.59","c_TimeBehind":"+6.46"},{"c_IntermediateFull":"1","c_Intermediate":"1","c_IntermediateShort":"1","c_ODF_Pos":"1","c_Rank":"25","c_Time":"2:21.31","c_TimeBehind":"+6.60"},{"c_IntermediateFull":"2","c_Intermediate":"2","c_IntermediateShort":"2","c_ODF_Pos":"2","c_Rank":"25","c_Time":"2:33.52","c_TimeBehind":"+6.79"},{"c_IntermediateFull":"3","c_Intermediate":"3","c_IntermediateShort":"3","c_ODF_Pos":"3","c_Rank":"25","c_Time":"2:44.72","c_TimeBehind":"+7.04"},{"c_IntermediateFull":"4","c_Intermediate":"4","c_IntermediateShort":"4","c_ODF_Pos":"4","c_Rank":"25","c_Time":"2:57.30","c_TimeBehind":"+7.45"},{"c_IntermediateFull":"Finish","c_Intermediate":"Finish","c_IntermediateShort":"Finish","c_ODF_Pos":"F","c_Rank":"25","c_Time":"3:08.37","c_TimeBehind":"+7.88"}],"c_ResultNeededForRankList_Header":{},"ResultNeededForRankList":[],"FSK":{}},"LeadingParticipant":{"n_ParticipantType":[1],"n_ParticipantID":[1013057],"c_Participant":["GROTHEER Christopher"],"c_ParticipantShort":["GROTHEER C"],"c_ParticipantFirstName":["Christopher"],"c_ParticipantLastName":["Grotheer"],"c_Bib":["4"],"n_StartOrder":[1],"NOC":{"n_ID":[2],"n_GeoID":[2206],"c_Name":["Germany"],"c_Short":["GER"]},"TeamMemberList":[],"c_Rank":["1"],"c_Rank_Header":{},"c_Result":["1:00.16"],"c_Result_Header":{},"c_OverallRank":["1"],"c_OverallRank_Header":{},"c_OverallResult":["3:00.49"],"c_OverallResult_Header":{},"c_ResultInfo_1":["130.1"],"c_ResultInfo_1_Header":{},"c_ResultInfo_2":{},"c_ResultInfo_2_Header":{},"c_ResultInfo_3":{},"c_ResultInfo_3_Header":{},"c_ResultInfo_4":{},"c_ResultInfo_4_Header":{},"c_ResultInfo_5":{},"c_ResultInfo_5_Header":{},"c_ResultInfo_6":{},"c_ResultInfo_6_Header":{},"c_ResultInfo_7":{},"c_ResultInfo_7_Header":{},"c_ResultInfo_8":{},"c_ResultInfo_8_Header":{},"c_ResultInfo_9":{},"c_ResultInfo_9_Header":{},"c_ResultInfo_10":{},"c_ResultInfo_10_Header":{},"c_ResultInfo_11":{},"c_ResultInfo_11_Header":{},"c_ResultInfo_12":{},"c_ResultInfo_12_Header":{},"c_ResultInfo_13":{},"c_ResultInfo_13_Header":{},"c_ResultInfo_14":{},"c_ResultInfo_14_Header":{},"c_ResultInfo_15":{},"c_ResultInfo_15_Header":{},"IntermediateResultList":[{"c_IntermediateFull":"Start","c_Intermediate":"Start","c_IntermediateShort":"Start","c_ODF_Pos":"S","c_Time":"2:05.13"},{"c_IntermediateFull":"1","c_Intermediate":"1","c_IntermediateShort":"1","c_ODF_Pos":"1","c_Time":"2:14.71"},{"c_IntermediateFull":"2","c_Intermediate":"2","c_IntermediateShort":"2","c_ODF_Pos":"2","c_Time":"2:26.73"},{"c_IntermediateFull":"3","c_Intermediate":"3","c_IntermediateShort":"3","c_ODF_Pos":"3","c_Time":"2:37.68"},{"c_IntermediateFull":"4","c_Intermediate":"4","c_IntermediateShort":"4","c_ODF_Pos":"4","c_Time":"2:49.85"},{"c_IntermediateFull":"Finish","c_Intermediate":"Finish","c_IntermediateShort":"Finish","c_ODF_Pos":"F","c_Time":"3:00.49"}],"c_ResultNeededForRankList_Header":{},"ResultNeededForRankList":[],"FSK":{}},"NextParticipant":{"n_ParticipantType":{},"n_ParticipantID":{},"c_Participant":{},"c_ParticipantShort":{},"c_ParticipantFirstName":{},"c_ParticipantLastName":{},"c_Bib":{},"n_StartOrder":{},"NOC":{"n_ID":{},"n_GeoID":{},"c_Name":{},"c_Short":{}},"TeamMemberList":[]},"Tracker":{"ColumnHeaders":{},"ParticipantList":[]},"IntermediateLeaders":{"ColumnHeaders":{},"IntermediateLeaderList":[]},"Race":{"ColumnHeaders":{},"Race":{}},"H2hRace":{"ColumnHeaders":{},"Race":{}},"H2hCompetition":{"c_Phase":{},"Competitor1":{},"Competitor2":{},"RunList":[]}},"Preview":{"MajorResultsInfo":{},"ParticipantList":[]},"StartList":{"PhaseList":[{"n_PhaseID":2412932,"c_Phase":"Run 3","n_PhaseSortNr":1,"n_PhaseEventTypeID":1,"DateTimes":{"Start":{"c_Local":"2022-02-11T20:20:00","d_Local":"/Date(1644610800000+0000)/","n_Local":20220211,"c_UTC":"2022-02-11T12:20:00","d_UTC":"/Date(1644582000000+0000)/","n_UTC":20220211},"End":{"c_Local":"2022-02-11T21:15:00","d_Local":"/Date(1644614100000+0000)/","n_Local":20220211,"c_UTC":"2022-02-11T13:15:00","d_UTC":"/Date(1644585300000+0000)/","n_UTC":20220211}},"c_Participant_Header":"Name","c_StartListInfo_1_Header":"Order","c_StartListInfo_2_Header":"Bib","ParticipantList":[{"n_ParticipantType":1,"n_ParticipantID":1013057,"c_Participant":"GROTHEER Christopher","c_ParticipantShort":"GROTHEER C","c_ParticipantFirstName":"Christopher","c_ParticipantLastName":"Grotheer","c_Bib":"4","n_StartOrder":1,"c_StartListInfo_1":"1","c_StartListInfo_2":"4","NOC":{"n_ID":2,"n_GeoID":2206,"c_Name":"Germany","c_Short":"GER"},"n_BirthDate":19920731,"n_HeightMillimetres":1800,"n_HeightInches":70,"TeamMemberList":[]},{"n_ParticipantType":1,"n_ParticipantID":1012974,"c_Participant":"JUNGK Axel","c_ParticipantShort":"JUNGK A","c_ParticipantFirstName":"Axel","c_ParticipantLastName":"Jungk","c_Bib":"8","n_StartOrder":2,"c_StartListInfo_1":"2","c_StartListInfo_2":"8","NOC":{"n_ID":2,"n_GeoID":2206,"c_Name":"Germany","c_Short":"GER"},"n_BirthDate":19910305,"n_HeightMillimetres":1840,"n_HeightInches":72,"TeamMemberList":[]},{"n_ParticipantType":1,"n_ParticipantID":1469883,"c_Participant":"YAN Wengang","c_ParticipantShort":"YAN W","c_ParticipantFirstName":"Wengang","c_ParticipantLastName":"Yan","c_Bib":"18","n_StartOrder":3,"c_StartListInfo_1":"3","c_StartListInfo_2":"18","NOC":{"n_ID":26,"n_GeoID":2770,"c_Name":"China","c_Short":"CHN"},"n_BirthDate":19970701,"n_HeightMillimetres":1830,"n_HeightInches":72,"TeamMemberList":[]},{"n_ParticipantType":1,"n_ParticipantID":1475763,"c_Participant":"RUKOSUEV Evgeniy","c_ParticipantShort":"RUKOSUEV E","c_ParticipantFirstName":"Evgeniy","c_ParticipantLastName":"Rukosuev","c_Bib":"12","n_StartOrder":4,"c_StartListInfo_1":"4","c_StartListInfo_2":"12","NOC":{"n_ID":23062,"n_GeoID":73035,"c_Name":"ROC","c_Short":"ROC"},"n_BirthDate":19990902,"n_HeightMillimetres":1750,"n_HeightInches":68,"TeamMemberList":[]},{"n_ParticipantType":1,"n_ParticipantID":577451,"c_Participant":"TRETIAKOV Alexander","c_ParticipantShort":"TRETIAKOV A","c_ParticipantFirstName":"Alexander","c_ParticipantLastName":"Tretiakov","c_Bib":"5","n_StartOrder":5,"c_StartListInfo_1":"5","c_StartListInfo_2":"5","NOC":{"n_ID":23062,"n_GeoID":73035,"c_Name":"ROC","c_Short":"ROC"},"n_BirthDate":19850419,"n_HeightMillimetres":1840,"n_HeightInches":72,"TeamMemberList":[]},{"n_ParticipantType":1,"n_ParticipantID":343478,"c_Participant":"DUKURS Martins","c_ParticipantShort":"DUKURS M","c_ParticipantFirstName":"Martins","c_ParticipantLastName":"Dukurs","c_Bib":"7","n_StartOrder":6,"c_StartListInfo_1":"6","c_StartListInfo_2":"7","NOC":{"n_ID":9,"n_GeoID":2218,"c_Name":"Latvia","c_Short":"LAT"},"n_BirthDate":19840331,"n_HeightMillimetres":1790,"n_HeightInches":70,"TeamMemberList":[]},{"n_ParticipantType":1,"n_ParticipantID":1945980,"c_Participant":"YIN Zheng","c_ParticipantShort":"YIN Z","c_ParticipantFirstName":"Zheng","c_ParticipantLastName":"Yin","c_Bib":"21","n_StartOrder":7,"c_StartListInfo_1":"7","c_StartListInfo_2":"21","NOC":{"n_ID":26,"n_GeoID":2770,"c_Name":"China","c_Short":"CHN"},"n_BirthDate":19960307,"TeamMemberList":[]},{"n_ParticipantType":1,"n_ParticipantID":343479,"c_Participant":"DUKURS Tomass","c_ParticipantShort":"DUKURS T","c_ParticipantFirstName":"Tomass","c_ParticipantLastName":"Dukurs","c_Bib":"6","n_StartOrder":8,"c_StartListInfo_1":"8","c_StartListInfo_2":"6","NOC":{"n_ID":9,"n_GeoID":2218,"c_Name":"Latvia","c_Short":"LAT"},"n_BirthDate":19810702,"n_HeightMillimetres":1860,"n_HeightInches":73,"TeamMemberList":[]},{"n_ParticipantType":1,"n_ParticipantID":718634,"c_Participant":"GASSNER Alexander","c_ParticipantShort":"GASSNER A","c_ParticipantFirstName":"Alexander","c_ParticipantLastName":"Gassner","c_Bib":"13","n_StartOrder":9,"c_StartListInfo_1":"9","c_StartListInfo_2":"13","NOC":{"n_ID":2,"n_GeoID":2206,"c_Name":"Germany","c_Short":"GER"},"n_BirthDate":19890809,"n_HeightMillimetres":1730,"n_HeightInches":68,"TeamMemberList":[]},{"n_ParticipantType":1,"n_ParticipantID":1339613,"c_Participant":"JUNG Seunggi","c_ParticipantShort":"JUNG S","c_ParticipantFirstName":"Seunggi","c_ParticipantLastName":"Jung","c_Bib":"10","n_StartOrder":10,"c_StartListInfo_1":"10","c_StartListInfo_2":"10","NOC":{"n_ID":106,"n_GeoID":4391,"c_Name":"South Korea","c_Short":"KOR"},"n_BirthDate":19990317,"n_HeightMillimetres":1750,"n_HeightInches":68,"TeamMemberList":[]},{"n_ParticipantType":1,"n_ParticipantID":1939046,"c_Participant":"BAGNIS Amedeo","c_ParticipantShort":"BAGNIS A","c_ParticipantFirstName":"Amedeo","c_ParticipantLastName":"Bagnis","c_Bib":"16","n_StartOrder":11,"c_StartListInfo_1":"11","c_StartListInfo_2":"16","NOC":{"n_ID":6,"n_GeoID":2210,"c_Name":"Italy","c_Short":"ITA"},"n_BirthDate":19991111,"TeamMemberList":[]},{"n_ParticipantType":1,"n_ParticipantID":1221503,"c_Participant":"SUNG-BIN Yun","c_ParticipantShort":"SUNG-BIN Y","c_ParticipantFirstName":"Sungbin","c_ParticipantLastName":"Yun","c_Bib":"11","n_StartOrder":12,"c_StartListInfo_1":"12","c_StartListInfo_2":"11","NOC":{"n_ID":106,"n_GeoID":4391,"c_Name":"South Korea","c_Short":"KOR"},"n_BirthDate":19940523,"n_HeightMillimetres":1780,"n_HeightInches":70,"TeamMemberList":[]},{"n_ParticipantType":1,"n_ParticipantID":1475806,"c_Participant":"MAIER Samuel","c_ParticipantShort":"MAIER S","c_ParticipantFirstName":"Samuel","c_ParticipantLastName":"Maier","c_Bib":"14","n_StartOrder":13,"c_StartListInfo_1":"13","c_StartListInfo_2":"14","NOC":{"n_ID":151,"n_GeoID":2219,"c_Name":"Austria","c_Short":"AUT"},"n_BirthDate":19991003,"TeamMemberList":[]},{"n_ParticipantType":1,"n_ParticipantID":1847537,"c_Participant":"WESTON Matt","c_ParticipantShort":"WESTON M","c_ParticipantFirstName":"Matt","c_ParticipantLastName":"Weston","c_Bib":"9","n_StartOrder":14,"c_StartListInfo_1":"14","c_StartListInfo_2":"9","NOC":{"n_ID":211,"n_GeoID":4058,"c_Name":"Great Britain","c_Short":"GBR"},"n_BirthDate":19970302,"TeamMemberList":[]},{"n_ParticipantType":1,"n_ParticipantID":834443,"c_Participant":"GASPARI Mattia","c_ParticipantShort":"GASPARI M","c_ParticipantFirstName":"Mattia","c_ParticipantLastName":"Gaspari","c_Bib":"17","n_StartOrder":15,"c_StartListInfo_1":"15","c_StartListInfo_2":"17","NOC":{"n_ID":6,"n_GeoID":2210,"c_Name":"Italy","c_Short":"ITA"},"n_BirthDate":19930914,"n_HeightMillimetres":1800,"n_HeightInches":70,"TeamMemberList":[]},{"n_ParticipantType":1,"n_ParticipantID":1353104,"c_Participant":"HERASKEVYCH Vladyslav","c_ParticipantShort":"HERASKEVYCH V","c_ParticipantFirstName":"Vladyslav","c_ParticipantLastName":"Heraskevych","c_Bib":"15","n_StartOrder":16,"c_StartListInfo_1":"16","c_StartListInfo_2":"15","NOC":{"n_ID":13,"n_GeoID":2232,"c_Name":"Ukraine","c_Short":"UKR"},"n_BirthDate":19990112,"n_HeightMillimetres":1860,"n_HeightInches":73,"TeamMemberList":[]},{"n_ParticipantType":1,"n_ParticipantID":1495443,"c_Participant":"WYATT Marcus","c_ParticipantShort":"WYATT M","c_ParticipantFirstName":"Marcus","c_ParticipantLastName":"Wyatt","c_Bib":"19","n_StartOrder":17,"c_StartListInfo_1":"17","c_StartListInfo_2":"19","NOC":{"n_ID":211,"n_GeoID":4058,"c_Name":"Great Britain","c_Short":"GBR"},"n_BirthDate":19911214,"TeamMemberList":[]},{"n_ParticipantType":1,"n_ParticipantID":1563857,"c_Participant":"SCHLINTNER Alexander","c_ParticipantShort":"SCHLINTNER A","c_ParticipantFirstName":"Alexander","c_ParticipantLastName":"Schlintner","c_Bib":"20","n_StartOrder":18,"c_StartListInfo_1":"18","c_StartListInfo_2":"20","NOC":{"n_ID":151,"n_GeoID":2219,"c_Name":"Austria","c_Short":"AUT"},"n_BirthDate":19980127,"TeamMemberList":[]},{"n_ParticipantType":1,"n_ParticipantID":1731352,"c_Participant":"ENZIE Blake","c_ParticipantShort":"ENZIE B","c_ParticipantFirstName":"Blake","c_ParticipantLastName":"Enzie","c_Bib":"24","n_StartOrder":19,"c_StartListInfo_1":"19","c_StartListInfo_2":"24","NOC":{"n_ID":159,"n_GeoID":2231,"c_Name":"Canada","c_Short":"CAN"},"n_BirthDate":20010902,"TeamMemberList":[]},{"n_ParticipantType":1,"n_ParticipantID":1139516,"c_Participant":"CRUMPTON Nathan","c_ParticipantShort":"CRUMPTON N","c_ParticipantFirstName":"Nathan","c_ParticipantLastName":"Crumpton","c_Bib":"22","n_StartOrder":20,"c_StartListInfo_1":"20","c_StartListInfo_2":"22","NOC":{"n_ID":258,"n_GeoID":9600,"c_Name":"American Samoa","c_Short":"ASA"},"n_BirthDate":19851009,"n_HeightMillimetres":1820,"n_HeightInches":71,"TeamMemberList":[]},{"n_ParticipantType":1,"n_ParticipantID":1482343,"c_Participant":"BLASER Andrew","c_ParticipantShort":"BLASER A","c_ParticipantFirstName":"Andrew","c_ParticipantLastName":"Blaser","c_Bib":"2","n_StartOrder":21,"c_StartListInfo_1":"21","c_StartListInfo_2":"2","NOC":{"n_ID":5,"n_GeoID":2209,"c_Name":"United States","c_Short":"USA"},"n_BirthDate":19890508,"TeamMemberList":[]},{"n_ParticipantType":1,"n_ParticipantID":1234238,"c_Participant":"SIEBER Basil","c_ParticipantShort":"SIEBER B","c_ParticipantFirstName":"Basil","c_ParticipantLastName":"Sieber","c_Bib":"25","n_StartOrder":22,"c_StartListInfo_1":"22","c_StartListInfo_2":"25","NOC":{"n_ID":149,"n_GeoID":2213,"c_Name":"Switzerland","c_Short":"SUI"},"n_BirthDate":19950614,"n_HeightMillimetres":1810,"n_HeightInches":71,"TeamMemberList":[]},{"n_ParticipantType":1,"n_ParticipantID":1939038,"c_Participant":"ROMANOV Daniil","c_ParticipantShort":"ROMANOV D","c_ParticipantFirstName":"Daniil","c_ParticipantLastName":"Romanov","c_Bib":"3","n_StartOrder":23,"c_StartListInfo_1":"23","c_StartListInfo_2":"3","NOC":{"n_ID":23062,"n_GeoID":73035,"c_Name":"ROC","c_Short":"ROC"},"n_BirthDate":19940308,"TeamMemberList":[]},{"n_ParticipantType":1,"n_ParticipantID":658631,"c_Participant":"MIRAMBELL Ander","c_ParticipantShort":"MIRAMBELL A","c_ParticipantFirstName":"Ander","c_ParticipantLastName":"Mirambell","c_Bib":"1","n_StartOrder":24,"c_StartListInfo_1":"24","c_StartListInfo_2":"1","NOC":{"n_ID":145,"n_GeoID":2203,"c_Name":"Spain","c_Short":"ESP"},"n_BirthDate":19830217,"n_HeightMillimetres":1820,"n_HeightInches":71,"TeamMemberList":[]},{"n_ParticipantType":1,"n_ParticipantID":1125020,"c_Participant":"TIMMINGS Nicholas","c_ParticipantShort":"TIMMINGS N","c_ParticipantFirstName":"Nicholas","c_ParticipantLastName":"Timmings","c_Bib":"23","n_StartOrder":25,"c_StartListInfo_1":"25","c_StartListInfo_2":"23","NOC":{"n_ID":157,"n_GeoID":2229,"c_Name":"Australia","c_Short":"AUS"},"n_BirthDate":19901229,"n_HeightMillimetres":1820,"n_HeightInches":71,"TeamMemberList":[]}]}]},"Result":{"IntermediatePhaseList":[],"PhaseList":[{"n_PhaseID":2412932,"c_Phase":"Run 3","n_PhaseSortNr":3,"n_PhaseEventTypeID":1,"DateTimes":{"Start":{"c_Local":"2022-02-11T20:20:00","d_Local":"/Date(1644610800000+0000)/","n_Local":20220211,"c_UTC":"2022-02-11T12:20:00","d_UTC":"/Date(1644582000000+0000)/","n_UTC":20220211},"End":{"c_Local":"2022-02-11T21:15:00","d_Local":"/Date(1644614100000+0000)/","n_Local":20220211,"c_UTC":"2022-02-11T13:15:00","d_UTC":"/Date(1644585300000+0000)/","n_UTC":20220211}},"c_ScheduleStatus":"Finished","c_ODF_ScheduleStatus":"FINISHED","c_Rank_Header":"Rank","c_Participant_Header":"Name","c_Result_Header":"Time","c_ResultInfo_1_Header":"Top Speed (km/h)","c_ResultStatus":"Official","c_ODF_ResultStatus":"OFFICIAL","ResultPhaseList":[],"ParticipantList":[{"n_ParticipantType":1,"n_ParticipantID":1013057,"c_Participant":"GROTHEER Christopher","c_ParticipantShort":"GROTHEER C","c_ParticipantFirstName":"Christopher","c_ParticipantLastName":"Grotheer","c_Bib":"4","n_StartOrder":1,"NOC":{"n_ID":2,"n_GeoID":2206,"c_Name":"Germany","c_Short":"GER"},"n_Rank":1,"n_RankSort":1,"c_Rank":"1","c_Result":"1:00.16","c_ResultAbs":"1:00.16","n_TimeAbs":60160,"n_TimeRel":0,"c_ResultInfo_1":"130.1","b_Completed":true,"b_Upcoming":false,"n_BDF_StartTime":1518048001,"c_BDF_StartTime":"456828:24:56","n_BDF_VideoSessionID":235,"c_ClientStreamURL":"https://stream.nbcolympics.com/mens-skeleton-heats-3-4","TeamMemberList":[],"PhaseResultList":[]},{"n_ParticipantType":1,"n_ParticipantID":1012974,"c_Participant":"JUNGK Axel","c_ParticipantShort":"JUNGK A","c_ParticipantFirstName":"Axel","c_ParticipantLastName":"Jungk","c_Bib":"8","n_StartOrder":2,"NOC":{"n_ID":2,"n_GeoID":2206,"c_Name":"Germany","c_Short":"GER"},"n_Rank":2,"n_RankSort":2,"c_Rank":"2","c_Result":"+0.15","c_ResultAbs":"1:00.31","n_TimeAbs":60310,"n_TimeRel":150,"c_ResultInfo_1":"129.3","b_Completed":true,"b_Upcoming":false,"n_BDF_StartTime":1518048002,"c_BDF_StartTime":"456828:26:13","n_BDF_VideoSessionID":235,"c_ClientStreamURL":"https://stream.nbcolympics.com/mens-skeleton-heats-3-4","TeamMemberList":[],"PhaseResultList":[]},{"n_ParticipantType":1,"n_ParticipantID":577451,"c_Participant":"TRETIAKOV Alexander","c_ParticipantShort":"TRETIAKOV A","c_ParticipantFirstName":"Alexander","c_ParticipantLastName":"Tretiakov","c_Bib":"5","n_StartOrder":5,"NOC":{"n_ID":23062,"n_GeoID":73035,"c_Name":"ROC","c_Short":"ROC"},"n_Rank":3,"n_RankSort":3,"c_Rank":"3","c_Result":"+0.21","c_ResultAbs":"1:00.37","n_TimeAbs":60370,"n_TimeRel":210,"c_ResultInfo_1":"129.3","b_Completed":true,"b_Upcoming":false,"n_BDF_StartTime":1518048005,"c_BDF_StartTime":"456828:33:49","n_BDF_VideoSessionID":235,"c_ClientStreamURL":"https://stream.nbcolympics.com/mens-skeleton-heats-3-4","TeamMemberList":[],"PhaseResultList":[]},{"n_ParticipantType":1,"n_ParticipantID":1945980,"c_Participant":"YIN Zheng","c_ParticipantShort":"YIN Z","c_ParticipantFirstName":"Zheng","c_ParticipantLastName":"Yin","c_Bib":"21","n_StartOrder":7,"NOC":{"n_ID":26,"n_GeoID":2770,"c_Name":"China","c_Short":"CHN"},"n_Rank":4,"n_RankSort":4,"c_Rank":"4","c_Result":"+0.24","c_ResultAbs":"1:00.40","n_TimeAbs":60400,"n_TimeRel":240,"c_ResultInfo_1":"128.7","b_Completed":true,"b_Upcoming":false,"n_BDF_StartTime":1518048007,"c_BDF_StartTime":"456828:38:04","n_BDF_VideoSessionID":235,"c_ClientStreamURL":"https://stream.nbcolympics.com/mens-skeleton-heats-3-4","TeamMemberList":[],"PhaseResultList":[]},{"n_ParticipantType":1,"n_ParticipantID":343478,"c_Participant":"DUKURS Martins","c_ParticipantShort":"DUKURS M","c_ParticipantFirstName":"Martins","c_ParticipantLastName":"Dukurs","c_Bib":"7","n_StartOrder":6,"NOC":{"n_ID":9,"n_GeoID":2218,"c_Name":"Latvia","c_Short":"LAT"},"n_Rank":4,"n_RankSort":5,"c_Rank":"4","c_Result":"+0.24","c_ResultAbs":"1:00.40","n_TimeAbs":60400,"n_TimeRel":240,"c_ResultInfo_1":"128.0","b_Completed":true,"b_Upcoming":false,"n_BDF_StartTime":1518048006,"c_BDF_StartTime":"456828:37:06","n_BDF_VideoSessionID":235,"c_ClientStreamURL":"https://stream.nbcolympics.com/mens-skeleton-heats-3-4","TeamMemberList":[],"PhaseResultList":[]},{"n_ParticipantType":1,"n_ParticipantID":1469883,"c_Participant":"YAN Wengang","c_ParticipantShort":"YAN W","c_ParticipantFirstName":"Wengang","c_ParticipantLastName":"Yan","c_Bib":"18","n_StartOrder":3,"NOC":{"n_ID":26,"n_GeoID":2770,"c_Name":"China","c_Short":"CHN"},"n_Rank":6,"n_RankSort":6,"c_Rank":"6","c_Result":"+0.38","c_ResultAbs":"1:00.54","n_TimeAbs":60540,"n_TimeRel":380,"c_ResultInfo_1":"128.8","b_Completed":true,"b_Upcoming":false,"n_BDF_StartTime":1518048003,"c_BDF_StartTime":"456830:44:26","n_BDF_VideoSessionID":235,"c_ClientStreamURL":"https://stream.nbcolympics.com/mens-skeleton-heats-3-4","TeamMemberList":[],"PhaseResultList":[]},{"n_ParticipantType":1,"n_ParticipantID":1475763,"c_Participant":"RUKOSUEV Evgeniy","c_ParticipantShort":"RUKOSUEV E","c_ParticipantFirstName":"Evgeniy","c_ParticipantLastName":"Rukosuev","c_Bib":"12","n_StartOrder":4,"NOC":{"n_ID":23062,"n_GeoID":73035,"c_Name":"ROC","c_Short":"ROC"},"n_Rank":7,"n_RankSort":7,"c_Rank":"7","c_Result":"+0.40","c_ResultAbs":"1:00.56","n_TimeAbs":60560,"n_TimeRel":400,"c_ResultInfo_1":"128.4","b_Completed":true,"b_Upcoming":false,"n_BDF_StartTime":1518048004,"c_BDF_StartTime":"456828:31:42","n_BDF_VideoSessionID":235,"c_ClientStreamURL":"https://stream.nbcolympics.com/mens-skeleton-heats-3-4","TeamMemberList":[],"PhaseResultList":[]},{"n_ParticipantType":1,"n_ParticipantID":718634,"c_Participant":"GASSNER Alexander","c_ParticipantShort":"GASSNER A","c_ParticipantFirstName":"Alexander","c_ParticipantLastName":"Gassner","c_Bib":"13","n_StartOrder":9,"NOC":{"n_ID":2,"n_GeoID":2206,"c_Name":"Germany","c_Short":"GER"},"n_Rank":8,"n_RankSort":8,"c_Rank":"8","c_Result":"+0.46","c_ResultAbs":"1:00.62","n_TimeAbs":60620,"n_TimeRel":460,"c_ResultInfo_1":"128.4","b_Completed":true,"b_Upcoming":false,"n_BDF_StartTime":1518048009,"c_BDF_StartTime":"456828:42:33","n_BDF_VideoSessionID":235,"c_ClientStreamURL":"https://stream.nbcolympics.com/mens-skeleton-heats-3-4","TeamMemberList":[],"PhaseResultList":[]},{"n_ParticipantType":1,"n_ParticipantID":1339613,"c_Participant":"JUNG Seunggi","c_ParticipantShort":"JUNG S","c_ParticipantFirstName":"Seunggi","c_ParticipantLastName":"Jung","c_Bib":"10","n_StartOrder":10,"NOC":{"n_ID":106,"n_GeoID":4391,"c_Name":"South Korea","c_Short":"KOR"},"n_Rank":9,"n_RankSort":9,"c_Rank":"9","c_Result":"+0.53","c_ResultAbs":"1:00.69","n_TimeAbs":60690,"n_TimeRel":530,"c_ResultInfo_1":"127.9","b_Completed":true,"b_Upcoming":false,"n_BDF_StartTime":1518048010,"c_BDF_StartTime":"456829:15:53","n_BDF_VideoSessionID":235,"c_ClientStreamURL":"https://stream.nbcolympics.com/mens-skeleton-heats-3-4","TeamMemberList":[],"PhaseResultList":[]},{"n_ParticipantType":1,"n_ParticipantID":343479,"c_Participant":"DUKURS Tomass","c_ParticipantShort":"DUKURS T","c_ParticipantFirstName":"Tomass","c_ParticipantLastName":"Dukurs","c_Bib":"6","n_StartOrder":8,"NOC":{"n_ID":9,"n_GeoID":2218,"c_Name":"Latvia","c_Short":"LAT"},"n_Rank":10,"n_RankSort":10,"c_Rank":"10","c_Result":"+0.58","c_ResultAbs":"1:00.74","n_TimeAbs":60740,"n_TimeRel":580,"c_ResultInfo_1":"128.0","b_Completed":true,"b_Upcoming":false,"n_BDF_StartTime":1518048008,"c_BDF_StartTime":"456828:40:12","n_BDF_VideoSessionID":235,"c_ClientStreamURL":"https://stream.nbcolympics.com/mens-skeleton-heats-3-4","TeamMemberList":[],"PhaseResultList":[]},{"n_ParticipantType":1,"n_ParticipantID":1939046,"c_Participant":"BAGNIS Amedeo","c_ParticipantShort":"BAGNIS A","c_ParticipantFirstName":"Amedeo","c_ParticipantLastName":"Bagnis","c_Bib":"16","n_StartOrder":11,"NOC":{"n_ID":6,"n_GeoID":2210,"c_Name":"Italy","c_Short":"ITA"},"n_Rank":11,"n_RankSort":11,"c_Rank":"11","c_Result":"+0.67","c_ResultAbs":"1:00.83","n_TimeAbs":60830,"n_TimeRel":670,"c_ResultInfo_1":"129.3","b_Completed":true,"b_Upcoming":false,"n_BDF_StartTime":1518048011,"c_BDF_StartTime":"456828:46:54","n_BDF_VideoSessionID":235,"c_ClientStreamURL":"https://stream.nbcolympics.com/mens-skeleton-heats-3-4","TeamMemberList":[],"PhaseResultList":[]},{"n_ParticipantType":1,"n_ParticipantID":1221503,"c_Participant":"SUNG-BIN Yun","c_ParticipantShort":"SUNG-BIN Y","c_ParticipantFirstName":"Sungbin","c_ParticipantLastName":"Yun","c_Bib":"11","n_StartOrder":12,"NOC":{"n_ID":106,"n_GeoID":4391,"c_Name":"South Korea","c_Short":"KOR"},"n_Rank":12,"n_RankSort":12,"c_Rank":"12","c_Result":"+0.87","c_ResultAbs":"1:01.03","n_TimeAbs":61030,"n_TimeRel":870,"c_ResultInfo_1":"127.1","b_Completed":true,"b_Upcoming":false,"n_BDF_StartTime":1518048012,"c_BDF_StartTime":"456828:48:31","n_BDF_VideoSessionID":235,"c_ClientStreamURL":"https://stream.nbcolympics.com/mens-skeleton-heats-3-4","TeamMemberList":[],"PhaseResultList":[]},{"n_ParticipantType":1,"n_ParticipantID":1475806,"c_Participant":"MAIER Samuel","c_ParticipantShort":"MAIER S","c_ParticipantFirstName":"Samuel","c_ParticipantLastName":"Maier","c_Bib":"14","n_StartOrder":13,"NOC":{"n_ID":151,"n_GeoID":2219,"c_Name":"Austria","c_Short":"AUT"},"n_Rank":13,"n_RankSort":13,"c_Rank":"13","c_Result":"+0.89","c_ResultAbs":"1:01.05","n_TimeAbs":61050,"n_TimeRel":890,"c_ResultInfo_1":"128.5","b_Completed":true,"b_Upcoming":false,"n_BDF_StartTime":1518048013,"c_BDF_StartTime":"456828:50:59","n_BDF_VideoSessionID":235,"c_ClientStreamURL":"https://stream.nbcolympics.com/mens-skeleton-heats-3-4","TeamMemberList":[],"PhaseResultList":[]},{"n_ParticipantType":1,"n_ParticipantID":1847537,"c_Participant":"WESTON Matt","c_ParticipantShort":"WESTON M","c_ParticipantFirstName":"Matt","c_ParticipantLastName":"Weston","c_Bib":"9","n_StartOrder":14,"NOC":{"n_ID":211,"n_GeoID":4058,"c_Name":"Great Britain","c_Short":"GBR"},"n_Rank":14,"n_RankSort":14,"c_Rank":"14","c_Result":"+0.96","c_ResultAbs":"1:01.12","n_TimeAbs":61120,"n_TimeRel":960,"c_ResultInfo_1":"125.8","b_Completed":true,"b_Upcoming":false,"n_BDF_StartTime":1518048014,"c_BDF_StartTime":"456828:53:26","n_BDF_VideoSessionID":235,"c_ClientStreamURL":"https://stream.nbcolympics.com/mens-skeleton-heats-3-4","TeamMemberList":[],"PhaseResultList":[]},{"n_ParticipantType":1,"n_ParticipantID":834443,"c_Participant":"GASPARI Mattia","c_ParticipantShort":"GASPARI M","c_ParticipantFirstName":"Mattia","c_ParticipantLastName":"Gaspari","c_Bib":"17","n_StartOrder":15,"NOC":{"n_ID":6,"n_GeoID":2210,"c_Name":"Italy","c_Short":"ITA"},"n_Rank":15,"n_RankSort":15,"c_Rank":"15","c_Result":"+1.00","c_ResultAbs":"1:01.16","n_TimeAbs":61160,"n_TimeRel":1000,"c_ResultInfo_1":"127.2","b_Completed":true,"b_Upcoming":false,"n_BDF_StartTime":1518048015,"c_BDF_StartTime":"456828:55:19","n_BDF_VideoSessionID":235,"c_ClientStreamURL":"https://stream.nbcolympics.com/mens-skeleton-heats-3-4","TeamMemberList":[],"PhaseResultList":[]},{"n_ParticipantType":1,"n_ParticipantID":1495443,"c_Participant":"WYATT Marcus","c_ParticipantShort":"WYATT M","c_ParticipantFirstName":"Marcus","c_ParticipantLastName":"Wyatt","c_Bib":"19","n_StartOrder":17,"NOC":{"n_ID":211,"n_GeoID":4058,"c_Name":"Great Britain","c_Short":"GBR"},"n_Rank":16,"n_RankSort":16,"c_Rank":"16","c_Result":"+1.12","c_ResultAbs":"1:01.28","n_TimeAbs":61280,"n_TimeRel":1120,"c_ResultInfo_1":"126.3","b_Completed":true,"b_Upcoming":false,"n_BDF_StartTime":1518048017,"c_BDF_StartTime":"456828:59:39","n_BDF_VideoSessionID":235,"c_ClientStreamURL":"https://stream.nbcolympics.com/mens-skeleton-heats-3-4","TeamMemberList":[],"PhaseResultList":[]},{"n_ParticipantType":1,"n_ParticipantID":1139516,"c_Participant":"CRUMPTON Nathan","c_ParticipantShort":"CRUMPTON N","c_ParticipantFirstName":"Nathan","c_ParticipantLastName":"Crumpton","c_Bib":"22","n_StartOrder":20,"NOC":{"n_ID":258,"n_GeoID":9600,"c_Name":"American Samoa","c_Short":"ASA"},"n_Rank":17,"n_RankSort":17,"c_Rank":"17","c_Result":"+1.44","c_ResultAbs":"1:01.60","n_TimeAbs":61600,"n_TimeRel":1440,"c_ResultInfo_1":"126.1","b_Completed":true,"b_Upcoming":false,"n_BDF_StartTime":1518048020,"c_BDF_StartTime":"456829:01:34","n_BDF_VideoSessionID":235,"c_ClientStreamURL":"https://stream.nbcolympics.com/mens-skeleton-heats-3-4","TeamMemberList":[],"PhaseResultList":[]},{"n_ParticipantType":1,"n_ParticipantID":1353104,"c_Participant":"HERASKEVYCH Vladyslav","c_ParticipantShort":"HERASKEVYCH V","c_ParticipantFirstName":"Vladyslav","c_ParticipantLastName":"Heraskevych","c_Bib":"15","n_StartOrder":16,"NOC":{"n_ID":13,"n_GeoID":2232,"c_Name":"Ukraine","c_Short":"UKR"},"n_Rank":18,"n_RankSort":18,"c_Rank":"18","c_Result":"+1.46","c_ResultAbs":"1:01.62","n_TimeAbs":61620,"n_TimeRel":1460,"c_ResultInfo_1":"127.6","b_Completed":true,"b_Upcoming":false,"n_BDF_StartTime":1518048016,"c_BDF_StartTime":"456828:57:59","n_BDF_VideoSessionID":235,"c_ClientStreamURL":"https://stream.nbcolympics.com/mens-skeleton-heats-3-4","TeamMemberList":[],"PhaseResultList":[]},{"n_ParticipantType":1,"n_ParticipantID":1563857,"c_Participant":"SCHLINTNER Alexander","c_ParticipantShort":"SCHLINTNER A","c_ParticipantFirstName":"Alexander","c_ParticipantLastName":"Schlintner","c_Bib":"20","n_StartOrder":18,"NOC":{"n_ID":151,"n_GeoID":2219,"c_Name":"Austria","c_Short":"AUT"},"n_Rank":19,"n_RankSort":19,"c_Rank":"19","c_Result":"+1.50","c_ResultAbs":"1:01.66","n_TimeAbs":61660,"n_TimeRel":1500,"c_ResultInfo_1":"126.6","b_Completed":true,"b_Upcoming":false,"n_BDF_StartTime":1518048018,"c_BDF_StartTime":"456829:01:19","n_BDF_VideoSessionID":235,"c_ClientStreamURL":"https://stream.nbcolympics.com/mens-skeleton-heats-3-4","TeamMemberList":[],"PhaseResultList":[]},{"n_ParticipantType":1,"n_ParticipantID":1125020,"c_Participant":"TIMMINGS Nicholas","c_ParticipantShort":"TIMMINGS N","c_ParticipantFirstName":"Nicholas","c_ParticipantLastName":"Timmings","c_Bib":"23","n_StartOrder":25,"NOC":{"n_ID":157,"n_GeoID":2229,"c_Name":"Australia","c_Short":"AUS"},"n_Rank":20,"n_RankSort":20,"c_Rank":"20","c_Result":"+1.62","c_ResultAbs":"1:01.78","n_TimeAbs":61780,"n_TimeRel":1620,"c_ResultInfo_1":"126.0","b_Completed":true,"b_Upcoming":false,"n_BDF_StartTime":1518048025,"c_BDF_StartTime":"456829:12:19","n_BDF_VideoSessionID":235,"c_ClientStreamURL":"https://stream.nbcolympics.com/mens-skeleton-heats-3-4","TeamMemberList":[],"PhaseResultList":[]},{"n_ParticipantType":1,"n_ParticipantID":1731352,"c_Participant":"ENZIE Blake","c_ParticipantShort":"ENZIE B","c_ParticipantFirstName":"Blake","c_ParticipantLastName":"Enzie","c_Bib":"24","n_StartOrder":19,"NOC":{"n_ID":159,"n_GeoID":2231,"c_Name":"Canada","c_Short":"CAN"},"n_Rank":21,"n_RankSort":21,"c_Rank":"21","c_Result":"+1.77","c_ResultAbs":"1:01.93","n_TimeAbs":61930,"n_TimeRel":1770,"c_ResultInfo_1":"124.9","b_Completed":true,"b_Upcoming":false,"n_BDF_StartTime":1518048019,"c_BDF_StartTime":"456829:03:13","n_BDF_VideoSessionID":235,"c_ClientStreamURL":"https://stream.nbcolympics.com/mens-skeleton-heats-3-4","TeamMemberList":[],"PhaseResultList":[]},{"n_ParticipantType":1,"n_ParticipantID":1482343,"c_Participant":"BLASER Andrew","c_ParticipantShort":"BLASER A","c_ParticipantFirstName":"Andrew","c_ParticipantLastName":"Blaser","c_Bib":"2","n_StartOrder":21,"NOC":{"n_ID":5,"n_GeoID":2209,"c_Name":"United States","c_Short":"USA"},"n_Rank":22,"n_RankSort":22,"c_Rank":"22","c_Result":"+1.94","c_ResultAbs":"1:02.10","n_TimeAbs":62100,"n_TimeRel":1940,"c_ResultInfo_1":"122.6","b_Completed":true,"b_Upcoming":false,"n_BDF_StartTime":1518048021,"c_BDF_StartTime":"456829:06:48","n_BDF_VideoSessionID":235,"c_ClientStreamURL":"https://stream.nbcolympics.com/mens-skeleton-heats-3-4","TeamMemberList":[],"PhaseResultList":[]},{"n_ParticipantType":1,"n_ParticipantID":1939038,"c_Participant":"ROMANOV Daniil","c_ParticipantShort":"ROMANOV D","c_ParticipantFirstName":"Daniil","c_ParticipantLastName":"Romanov","c_Bib":"3","n_StartOrder":23,"NOC":{"n_ID":23062,"n_GeoID":73035,"c_Name":"ROC","c_Short":"ROC"},"n_Rank":23,"n_RankSort":23,"c_Rank":"23","c_Result":"+2.04","c_ResultAbs":"1:02.20","n_TimeAbs":62200,"n_TimeRel":2040,"c_ResultInfo_1":"122.3","b_Completed":true,"b_Upcoming":false,"n_BDF_StartTime":1518048023,"c_BDF_StartTime":"456829:15:32","n_BDF_VideoSessionID":235,"c_ClientStreamURL":"https://stream.nbcolympics.com/mens-skeleton-heats-3-4","TeamMemberList":[],"PhaseResultList":[]},{"n_ParticipantType":1,"n_ParticipantID":658631,"c_Participant":"MIRAMBELL Ander","c_ParticipantShort":"MIRAMBELL A","c_ParticipantFirstName":"Ander","c_ParticipantLastName":"Mirambell","c_Bib":"1","n_StartOrder":24,"NOC":{"n_ID":145,"n_GeoID":2203,"c_Name":"Spain","c_Short":"ESP"},"n_Rank":24,"n_RankSort":24,"c_Rank":"24","c_Result":"+2.18","c_ResultAbs":"1:02.34","n_TimeAbs":62340,"n_TimeRel":2180,"c_ResultInfo_1":"124.4","b_Completed":true,"b_Upcoming":false,"n_BDF_StartTime":1518048024,"c_BDF_StartTime":"456829:12:44","n_BDF_VideoSessionID":235,"c_ClientStreamURL":"https://stream.nbcolympics.com/mens-skeleton-heats-3-4","TeamMemberList":[],"PhaseResultList":[]},{"n_ParticipantType":1,"n_ParticipantID":1234238,"c_Participant":"SIEBER Basil","c_ParticipantShort":"SIEBER B","c_ParticipantFirstName":"Basil","c_ParticipantLastName":"Sieber","c_Bib":"25","n_StartOrder":22,"NOC":{"n_ID":149,"n_GeoID":2213,"c_Name":"Switzerland","c_Short":"SUI"},"n_Rank":25,"n_RankSort":25,"c_Rank":"25","c_Result":"+2.56","c_ResultAbs":"1:02.72","n_TimeAbs":62720,"n_TimeRel":2560,"c_ResultInfo_1":"124.7","b_Completed":true,"b_Upcoming":false,"n_BDF_StartTime":1518048022,"c_BDF_StartTime":"456829:08:45","n_BDF_VideoSessionID":235,"c_ClientStreamURL":"https://stream.nbcolympics.com/mens-skeleton-heats-3-4","TeamMemberList":[],"PhaseResultList":[]}]}],"EventPhaseRanking":{}},"Standings":{"Phase":{"n_PhaseID":[2412932],"c_Phase":["Run 3"],"n_PhaseSortNr":[3],"n_PhaseEventTypeID":[1],"c_Rank_Header":["Rank"],"c_Participant_Header":["Name"],"c_Result_Header":["Time"],"c_ResultInfo_1_Header":{},"c_ResultInfo_2_Header":{},"c_ResultInfo_3_Header":{},"c_ResultInfo_4_Header":{},"n_BDF_StartTime":{},"c_BDF_StartTime":{},"n_BDF_VideoSessionID":{},"c_ClientStreamURL":{}},"ResultPhaseList":[{"n_PhaseID":2412930,"c_Phase":"Run 1","n_PhaseSortNr":1,"n_PhaseEventTypeID":1,"c_Result_Header":"Run 1"},{"n_PhaseID":2412931,"c_Phase":"Run 2","n_PhaseSortNr":2,"n_PhaseEventTypeID":1,"c_Result_Header":"Run 2"},{"n_PhaseID":2412932,"c_Phase":"Run 3","n_PhaseSortNr":3,"n_PhaseEventTypeID":1,"c_Result_Header":"Run 3"}],"ParticipantList":[{"n_ParticipantType":1,"n_ParticipantID":1013057,"c_Participant":"GROTHEER Christopher","c_ParticipantShort":"GROTHEER C","c_ParticipantFirstName":"Christopher","c_ParticipantLastName":"Grotheer","c_Bib":"4","n_StartOrder":1,"NOC":{"n_ID":2,"n_GeoID":2206,"c_Name":"Germany","c_Short":"GER"},"n_Rank":1,"n_RankSort":1,"c_Rank":"1","c_Result":"3:00.49","c_ResultAbs":"3:00.49","n_TimeAbs":180490,"n_TimeRel":0,"c_ODF_QualificationMark":"Q","b_DidNotAdvance":false,"TeamMemberList":[],"ResultPhaseList":[{"n_PhaseID":2412930,"n_Rank":1,"n_RankSort":1,"c_Rank":"1","c_Result":"1:00.00","c_ResultAbs":"1:00.00","n_TimeAbs":60000,"n_TimeRel":0,"n_BDF_StartTime":1518048004,"c_BDF_StartTime":"456793:36:00","n_BDF_VideoSessionID":233,"c_ClientStreamURL":"https://stream.nbcolympics.com/mens-skeleton-heats-1-2"},{"n_PhaseID":2412931,"n_Rank":1,"n_RankSort":1,"c_Rank":"1","c_Result":"1:00.33","c_ResultAbs":"1:00.33","n_TimeAbs":60330,"n_TimeRel":0,"n_BDF_StartTime":1518048020,"c_BDF_StartTime":"456795:38:00","n_BDF_VideoSessionID":233,"c_ClientStreamURL":"https://stream.nbcolympics.com/mens-skeleton-heats-1-2"},{"n_PhaseID":2412932,"n_Rank":1,"n_RankSort":1,"c_Rank":"1","c_Result":"1:00.16","c_ResultAbs":"1:00.16","n_TimeAbs":60160,"n_TimeRel":0,"n_BDF_StartTime":1518048001,"c_BDF_StartTime":"456828:20:00","n_BDF_VideoSessionID":235,"c_ClientStreamURL":"https://stream.nbcolympics.com/mens-skeleton-heats-3-4"}]},{"n_ParticipantType":1,"n_ParticipantID":1012974,"c_Participant":"JUNGK Axel","c_ParticipantShort":"JUNGK A","c_ParticipantFirstName":"Axel","c_ParticipantLastName":"Jungk","c_Bib":"8","n_StartOrder":2,"NOC":{"n_ID":2,"n_GeoID":2206,"c_Name":"Germany","c_Short":"GER"},"n_Rank":2,"n_RankSort":2,"c_Rank":"2","c_Result":"+0.85","c_ResultAbs":"3:01.34","n_TimeAbs":181340,"n_TimeRel":850,"c_ODF_QualificationMark":"Q","b_DidNotAdvance":false,"TeamMemberList":[],"ResultPhaseList":[{"n_PhaseID":2412930,"n_Rank":5,"n_RankSort":5,"c_Rank":"5","c_Result":"1:00.50","c_ResultAbs":"1:00.50","n_TimeAbs":60500,"n_TimeRel":500,"n_BDF_StartTime":1518048008,"c_BDF_StartTime":"456793:44:00","n_BDF_VideoSessionID":233,"c_ClientStreamURL":"https://stream.nbcolympics.com/mens-skeleton-heats-1-2"},{"n_PhaseID":2412931,"n_Rank":2,"n_RankSort":2,"c_Rank":"2","c_Result":"1:00.53","c_ResultAbs":"1:00.53","n_TimeAbs":60530,"n_TimeRel":200,"n_BDF_StartTime":1518048016,"c_BDF_StartTime":"456795:30:00","n_BDF_VideoSessionID":233,"c_ClientStreamURL":"https://stream.nbcolympics.com/mens-skeleton-heats-1-2"},{"n_PhaseID":2412932,"n_Rank":2,"n_RankSort":2,"c_Rank":"2","c_Result":"1:00.31","c_ResultAbs":"1:00.31","n_TimeAbs":60310,"n_TimeRel":150,"n_BDF_StartTime":1518048002,"c_BDF_StartTime":"456828:22:00","n_BDF_VideoSessionID":235,"c_ClientStreamURL":"https://stream.nbcolympics.com/mens-skeleton-heats-3-4"}]},{"n_ParticipantType":1,"n_ParticipantID":577451,"c_Participant":"TRETIAKOV Alexander","c_ParticipantShort":"TRETIAKOV A","c_ParticipantFirstName":"Alexander","c_ParticipantLastName":"Tretiakov","c_Bib":"5","n_StartOrder":5,"NOC":{"n_ID":23062,"n_GeoID":73035,"c_Name":"ROC","c_Short":"ROC"},"n_Rank":3,"n_RankSort":3,"c_Rank":"3","c_Result":"+1.08","c_ResultAbs":"3:01.57","n_TimeAbs":181570,"n_TimeRel":1080,"c_ODF_QualificationMark":"Q","b_DidNotAdvance":false,"TeamMemberList":[],"ResultPhaseList":[{"n_PhaseID":2412930,"n_Rank":2,"n_RankSort":2,"c_Rank":"2","c_Result":"1:00.36","c_ResultAbs":"1:00.36","n_TimeAbs":60360,"n_TimeRel":360,"n_BDF_StartTime":1518048005,"c_BDF_StartTime":"456793:38:00","n_BDF_VideoSessionID":233,"c_ClientStreamURL":"https://stream.nbcolympics.com/mens-skeleton-heats-1-2"},{"n_PhaseID":2412931,"n_Rank":8,"n_RankSort":8,"c_Rank":"8","c_Result":"1:00.84","c_ResultAbs":"1:00.84","n_TimeAbs":60840,"n_TimeRel":510,"n_BDF_StartTime":1518048019,"c_BDF_StartTime":"456795:36:00","n_BDF_VideoSessionID":233,"c_ClientStreamURL":"https://stream.nbcolympics.com/mens-skeleton-heats-1-2"},{"n_PhaseID":2412932,"n_Rank":3,"n_RankSort":3,"c_Rank":"3","c_Result":"1:00.37","c_ResultAbs":"1:00.37","n_TimeAbs":60370,"n_TimeRel":210,"n_BDF_StartTime":1518048005,"c_BDF_StartTime":"456828:28:00","n_BDF_VideoSessionID":235,"c_ClientStreamURL":"https://stream.nbcolympics.com/mens-skeleton-heats-3-4"}]},{"n_ParticipantType":1,"n_ParticipantID":1469883,"c_Participant":"YAN Wengang","c_ParticipantShort":"YAN W","c_ParticipantFirstName":"Wengang","c_ParticipantLastName":"Yan","c_Bib":"18","n_StartOrder":3,"NOC":{"n_ID":26,"n_GeoID":2770,"c_Name":"China","c_Short":"CHN"},"n_Rank":4,"n_RankSort":4,"c_Rank":"4","c_Result":"+1.13","c_ResultAbs":"3:01.62","n_TimeAbs":181620,"n_TimeRel":1130,"c_ODF_QualificationMark":"Q","b_DidNotAdvance":false,"TeamMemberList":[],"ResultPhaseList":[{"n_PhaseID":2412930,"n_Rank":3,"n_RankSort":3,"c_Rank":"3","c_Result":"1:00.43","c_ResultAbs":"1:00.43","n_TimeAbs":60430,"n_TimeRel":430,"n_BDF_StartTime":1518048018,"c_BDF_StartTime":"456794:04:00","n_BDF_VideoSessionID":233,"c_ClientStreamURL":"https://stream.nbcolympics.com/mens-skeleton-heats-1-2"},{"n_PhaseID":2412931,"n_Rank":4,"n_RankSort":4,"c_Rank":"4","c_Result":"1:00.65","c_ResultAbs":"1:00.65","n_TimeAbs":60650,"n_TimeRel":320,"n_BDF_StartTime":1518048018,"c_BDF_StartTime":"456795:34:00","n_BDF_VideoSessionID":233,"c_ClientStreamURL":"https://stream.nbcolympics.com/mens-skeleton-heats-1-2"},{"n_PhaseID":2412932,"n_Rank":6,"n_RankSort":6,"c_Rank":"6","c_Result":"1:00.54","c_ResultAbs":"1:00.54","n_TimeAbs":60540,"n_TimeRel":380,"n_BDF_StartTime":1518048003,"c_BDF_StartTime":"456828:24:00","n_BDF_VideoSessionID":235,"c_ClientStreamURL":"https://stream.nbcolympics.com/mens-skeleton-heats-3-4"}]},{"n_ParticipantType":1,"n_ParticipantID":343478,"c_Participant":"DUKURS Martins","c_ParticipantShort":"DUKURS M","c_ParticipantFirstName":"Martins","c_ParticipantLastName":"Dukurs","c_Bib":"7","n_StartOrder":6,"NOC":{"n_ID":9,"n_GeoID":2218,"c_Name":"Latvia","c_Short":"LAT"},"n_Rank":5,"n_RankSort":5,"c_Rank":"5","c_Result":"+1.15","c_ResultAbs":"3:01.64","n_TimeAbs":181640,"n_TimeRel":1150,"c_ODF_QualificationMark":"Q","b_DidNotAdvance":false,"TeamMemberList":[],"ResultPhaseList":[{"n_PhaseID":2412930,"n_Rank":6,"n_RankSort":6,"c_Rank":"6","c_Result":"1:00.62","c_ResultAbs":"1:00.62","n_TimeAbs":60620,"n_TimeRel":620,"n_BDF_StartTime":1518048007,"c_BDF_StartTime":"456793:42:00","n_BDF_VideoSessionID":233,"c_ClientStreamURL":"https://stream.nbcolympics.com/mens-skeleton-heats-1-2"},{"n_PhaseID":2412931,"n_Rank":3,"n_RankSort":3,"c_Rank":"3","c_Result":"1:00.62","c_ResultAbs":"1:00.62","n_TimeAbs":60620,"n_TimeRel":290,"n_BDF_StartTime":1518048015,"c_BDF_StartTime":"456795:28:00","n_BDF_VideoSessionID":233,"c_ClientStreamURL":"https://stream.nbcolympics.com/mens-skeleton-heats-1-2"},{"n_PhaseID":2412932,"n_Rank":4,"n_RankSort":4,"c_Rank":"4","c_Result":"1:00.40","c_ResultAbs":"1:00.40","n_TimeAbs":60400,"n_TimeRel":240,"n_BDF_StartTime":1518048006,"c_BDF_StartTime":"456828:30:00","n_BDF_VideoSessionID":235,"c_ClientStreamURL":"https://stream.nbcolympics.com/mens-skeleton-heats-3-4"}]},{"n_ParticipantType":1,"n_ParticipantID":1475763,"c_Participant":"RUKOSUEV Evgeniy","c_ParticipantShort":"RUKOSUEV E","c_ParticipantFirstName":"Evgeniy","c_ParticipantLastName":"Rukosuev","c_Bib":"12","n_StartOrder":4,"NOC":{"n_ID":23062,"n_GeoID":73035,"c_Name":"ROC","c_Short":"ROC"},"n_Rank":6,"n_RankSort":6,"c_Rank":"6","c_Result":"+1.27","c_ResultAbs":"3:01.76","n_TimeAbs":181760,"n_TimeRel":1270,"c_ODF_QualificationMark":"Q","b_DidNotAdvance":false,"TeamMemberList":[],"ResultPhaseList":[{"n_PhaseID":2412930,"n_Rank":4,"n_RankSort":4,"c_Rank":"4","c_Result":"1:00.48","c_ResultAbs":"1:00.48","n_TimeAbs":60480,"n_TimeRel":480,"n_BDF_StartTime":1518048012,"c_BDF_StartTime":"456793:52:00","n_BDF_VideoSessionID":233,"c_ClientStreamURL":"https://stream.nbcolympics.com/mens-skeleton-heats-1-2"},{"n_PhaseID":2412931,"n_Rank":6,"n_RankSort":6,"c_Rank":"6","c_Result":"1:00.72","c_ResultAbs":"1:00.72","n_TimeAbs":60720,"n_TimeRel":390,"n_BDF_StartTime":1518048017,"c_BDF_StartTime":"456795:32:00","n_BDF_VideoSessionID":233,"c_ClientStreamURL":"https://stream.nbcolympics.com/mens-skeleton-heats-1-2"},{"n_PhaseID":2412932,"n_Rank":7,"n_RankSort":7,"c_Rank":"7","c_Result":"1:00.56","c_ResultAbs":"1:00.56","n_TimeAbs":60560,"n_TimeRel":400,"n_BDF_StartTime":1518048004,"c_BDF_StartTime":"456828:26:00","n_BDF_VideoSessionID":235,"c_ClientStreamURL":"https://stream.nbcolympics.com/mens-skeleton-heats-3-4"}]},{"n_ParticipantType":1,"n_ParticipantID":1945980,"c_Participant":"YIN Zheng","c_ParticipantShort":"YIN Z","c_ParticipantFirstName":"Zheng","c_ParticipantLastName":"Yin","c_Bib":"21","n_StartOrder":7,"NOC":{"n_ID":26,"n_GeoID":2770,"c_Name":"China","c_Short":"CHN"},"n_Rank":7,"n_RankSort":7,"c_Rank":"7","c_Result":"+1.36","c_ResultAbs":"3:01.85","n_TimeAbs":181850,"n_TimeRel":1360,"c_ODF_QualificationMark":"Q","b_DidNotAdvance":false,"TeamMemberList":[],"ResultPhaseList":[{"n_PhaseID":2412930,"n_Rank":7,"n_RankSort":7,"c_Rank":"7","c_Result":"1:00.74","c_ResultAbs":"1:00.74","n_TimeAbs":60740,"n_TimeRel":740,"n_BDF_StartTime":1518048021,"c_BDF_StartTime":"456794:10:00","n_BDF_VideoSessionID":233,"c_ClientStreamURL":"https://stream.nbcolympics.com/mens-skeleton-heats-1-2"},{"n_PhaseID":2412931,"n_Rank":5,"n_RankSort":5,"c_Rank":"5","c_Result":"1:00.71","c_ResultAbs":"1:00.71","n_TimeAbs":60710,"n_TimeRel":380,"n_BDF_StartTime":1518048014,"c_BDF_StartTime":"456795:26:00","n_BDF_VideoSessionID":233,"c_ClientStreamURL":"https://stream.nbcolympics.com/mens-skeleton-heats-1-2"},{"n_PhaseID":2412932,"n_Rank":4,"n_RankSort":5,"c_Rank":"4","c_Result":"1:00.40","c_ResultAbs":"1:00.40","n_TimeAbs":60400,"n_TimeRel":240,"n_BDF_StartTime":1518048007,"c_BDF_StartTime":"456828:32:00","n_BDF_VideoSessionID":235,"c_ClientStreamURL":"https://stream.nbcolympics.com/mens-skeleton-heats-3-4"}]},{"n_ParticipantType":1,"n_ParticipantID":343479,"c_Participant":"DUKURS Tomass","c_ParticipantShort":"DUKURS T","c_ParticipantFirstName":"Tomass","c_ParticipantLastName":"Dukurs","c_Bib":"6","n_StartOrder":8,"NOC":{"n_ID":9,"n_GeoID":2218,"c_Name":"Latvia","c_Short":"LAT"},"n_Rank":8,"n_RankSort":8,"c_Rank":"8","c_Result":"+1.80","c_ResultAbs":"3:02.29","n_TimeAbs":182290,"n_TimeRel":1800,"c_ODF_QualificationMark":"Q","b_DidNotAdvance":false,"TeamMemberList":[],"ResultPhaseList":[{"n_PhaseID":2412930,"n_Rank":8,"n_RankSort":8,"c_Rank":"8","c_Result":"1:00.76","c_ResultAbs":"1:00.76","n_TimeAbs":60760,"n_TimeRel":760,"n_BDF_StartTime":1518048006,"c_BDF_StartTime":"456793:40:00","n_BDF_VideoSessionID":233,"c_ClientStreamURL":"https://stream.nbcolympics.com/mens-skeleton-heats-1-2"},{"n_PhaseID":2412931,"n_Rank":7,"n_RankSort":7,"c_Rank":"7","c_Result":"1:00.79","c_ResultAbs":"1:00.79","n_TimeAbs":60790,"n_TimeRel":460,"n_BDF_StartTime":1518048013,"c_BDF_StartTime":"456795:24:00","n_BDF_VideoSessionID":233,"c_ClientStreamURL":"https://stream.nbcolympics.com/mens-skeleton-heats-1-2"},{"n_PhaseID":2412932,"n_Rank":10,"n_RankSort":10,"c_Rank":"10","c_Result":"1:00.74","c_ResultAbs":"1:00.74","n_TimeAbs":60740,"n_TimeRel":580,"n_BDF_StartTime":1518048008,"c_BDF_StartTime":"456828:34:00","n_BDF_VideoSessionID":235,"c_ClientStreamURL":"https://stream.nbcolympics.com/mens-skeleton-heats-3-4"}]},{"n_ParticipantType":1,"n_ParticipantID":718634,"c_Participant":"GASSNER Alexander","c_ParticipantShort":"GASSNER A","c_ParticipantFirstName":"Alexander","c_ParticipantLastName":"Gassner","c_Bib":"13","n_StartOrder":9,"NOC":{"n_ID":2,"n_GeoID":2206,"c_Name":"Germany","c_Short":"GER"},"n_Rank":9,"n_RankSort":9,"c_Rank":"9","c_Result":"+1.86","c_ResultAbs":"3:02.35","n_TimeAbs":182350,"n_TimeRel":1860,"c_ODF_QualificationMark":"Q","b_DidNotAdvance":false,"TeamMemberList":[],"ResultPhaseList":[{"n_PhaseID":2412930,"n_Rank":9,"n_RankSort":9,"c_Rank":"9","c_Result":"1:00.87","c_ResultAbs":"1:00.87","n_TimeAbs":60870,"n_TimeRel":870,"n_BDF_StartTime":1518048013,"c_BDF_StartTime":"456793:54:00","n_BDF_VideoSessionID":233,"c_ClientStreamURL":"https://stream.nbcolympics.com/mens-skeleton-heats-1-2"},{"n_PhaseID":2412931,"n_Rank":9,"n_RankSort":9,"c_Rank":"9","c_Result":"1:00.86","c_ResultAbs":"1:00.86","n_TimeAbs":60860,"n_TimeRel":530,"n_BDF_StartTime":1518048012,"c_BDF_StartTime":"456795:22:00","n_BDF_VideoSessionID":233,"c_ClientStreamURL":"https://stream.nbcolympics.com/mens-skeleton-heats-1-2"},{"n_PhaseID":2412932,"n_Rank":8,"n_RankSort":8,"c_Rank":"8","c_Result":"1:00.62","c_ResultAbs":"1:00.62","n_TimeAbs":60620,"n_TimeRel":460,"n_BDF_StartTime":1518048009,"c_BDF_StartTime":"456828:36:00","n_BDF_VideoSessionID":235,"c_ClientStreamURL":"https://stream.nbcolympics.com/mens-skeleton-heats-3-4"}]},{"n_ParticipantType":1,"n_ParticipantID":1339613,"c_Participant":"JUNG Seunggi","c_ParticipantShort":"JUNG S","c_ParticipantFirstName":"Seunggi","c_ParticipantLastName":"Jung","c_Bib":"10","n_StartOrder":10,"NOC":{"n_ID":106,"n_GeoID":4391,"c_Name":"South Korea","c_Short":"KOR"},"n_Rank":10,"n_RankSort":10,"c_Rank":"10","c_Result":"+2.42","c_ResultAbs":"3:02.91","n_TimeAbs":182910,"n_TimeRel":2420,"c_ODF_QualificationMark":"Q","b_DidNotAdvance":false,"TeamMemberList":[],"ResultPhaseList":[{"n_PhaseID":2412930,"n_Rank":11,"n_RankSort":11,"c_Rank":"11","c_Result":"1:01.18","c_ResultAbs":"1:01.18","n_TimeAbs":61180,"n_TimeRel":1180,"n_BDF_StartTime":1518048010,"c_BDF_StartTime":"456793:48:00","n_BDF_VideoSessionID":233,"c_ClientStreamURL":"https://stream.nbcolympics.com/mens-skeleton-heats-1-2"},{"n_PhaseID":2412931,"n_Rank":10,"n_RankSort":10,"c_Rank":"10","c_Result":"1:01.04","c_ResultAbs":"1:01.04","n_TimeAbs":61040,"n_TimeRel":710,"n_BDF_StartTime":1518048010,"c_BDF_StartTime":"456795:18:00","n_BDF_VideoSessionID":233,"c_ClientStreamURL":"https://stream.nbcolympics.com/mens-skeleton-heats-1-2"},{"n_PhaseID":2412932,"n_Rank":9,"n_RankSort":9,"c_Rank":"9","c_Result":"1:00.69","c_ResultAbs":"1:00.69","n_TimeAbs":60690,"n_TimeRel":530,"n_BDF_StartTime":1518048010,"c_BDF_StartTime":"456828:38:00","n_BDF_VideoSessionID":235,"c_ClientStreamURL":"https://stream.nbcolympics.com/mens-skeleton-heats-3-4"}]},{"n_ParticipantType":1,"n_ParticipantID":1939046,"c_Participant":"BAGNIS Amedeo","c_ParticipantShort":"BAGNIS A","c_ParticipantFirstName":"Amedeo","c_ParticipantLastName":"Bagnis","c_Bib":"16","n_StartOrder":11,"NOC":{"n_ID":6,"n_GeoID":2210,"c_Name":"Italy","c_Short":"ITA"},"n_Rank":11,"n_RankSort":11,"c_Rank":"11","c_Result":"+2.58","c_ResultAbs":"3:03.07","n_TimeAbs":183070,"n_TimeRel":2580,"c_ODF_QualificationMark":"Q","b_DidNotAdvance":false,"TeamMemberList":[],"ResultPhaseList":[{"n_PhaseID":2412930,"n_Rank":10,"n_RankSort":10,"c_Rank":"10","c_Result":"1:01.05","c_ResultAbs":"1:01.05","n_TimeAbs":61050,"n_TimeRel":1050,"n_BDF_StartTime":1518048016,"c_BDF_StartTime":"456794:00:00","n_BDF_VideoSessionID":233,"c_ClientStreamURL":"https://stream.nbcolympics.com/mens-skeleton-heats-1-2"},{"n_PhaseID":2412931,"n_Rank":14,"n_RankSort":14,"c_Rank":"14","c_Result":"1:01.19","c_ResultAbs":"1:01.19","n_TimeAbs":61190,"n_TimeRel":860,"n_BDF_StartTime":1518048011,"c_BDF_StartTime":"456795:20:00","n_BDF_VideoSessionID":233,"c_ClientStreamURL":"https://stream.nbcolympics.com/mens-skeleton-heats-1-2"},{"n_PhaseID":2412932,"n_Rank":11,"n_RankSort":11,"c_Rank":"11","c_Result":"1:00.83","c_ResultAbs":"1:00.83","n_TimeAbs":60830,"n_TimeRel":670,"n_BDF_StartTime":1518048011,"c_BDF_StartTime":"456828:40:00","n_BDF_VideoSessionID":235,"c_ClientStreamURL":"https://stream.nbcolympics.com/mens-skeleton-heats-3-4"}]},{"n_ParticipantType":1,"n_ParticipantID":1221503,"c_Participant":"SUNG-BIN Yun","c_ParticipantShort":"SUNG-BIN Y","c_ParticipantFirstName":"Sungbin","c_ParticipantLastName":"Yun","c_Bib":"11","n_StartOrder":12,"NOC":{"n_ID":106,"n_GeoID":4391,"c_Name":"South Korea","c_Short":"KOR"},"n_Rank":12,"n_RankSort":12,"c_Rank":"12","c_Result":"+2.97","c_ResultAbs":"3:03.46","n_TimeAbs":183460,"n_TimeRel":2970,"c_ODF_QualificationMark":"Q","b_DidNotAdvance":false,"TeamMemberList":[],"ResultPhaseList":[{"n_PhaseID":2412930,"n_Rank":13,"n_RankSort":13,"c_Rank":"13","c_Result":"1:01.26","c_ResultAbs":"1:01.26","n_TimeAbs":61260,"n_TimeRel":1260,"n_BDF_StartTime":1518048011,"c_BDF_StartTime":"456793:50:00","n_BDF_VideoSessionID":233,"c_ClientStreamURL":"https://stream.nbcolympics.com/mens-skeleton-heats-1-2"},{"n_PhaseID":2412931,"n_Rank":13,"n_RankSort":13,"c_Rank":"13","c_Result":"1:01.17","c_ResultAbs":"1:01.17","n_TimeAbs":61170,"n_TimeRel":840,"n_BDF_StartTime":1518048008,"c_BDF_StartTime":"456795:14:00","n_BDF_VideoSessionID":233,"c_ClientStreamURL":"https://stream.nbcolympics.com/mens-skeleton-heats-1-2"},{"n_PhaseID":2412932,"n_Rank":12,"n_RankSort":12,"c_Rank":"12","c_Result":"1:01.03","c_ResultAbs":"1:01.03","n_TimeAbs":61030,"n_TimeRel":870,"n_BDF_StartTime":1518048012,"c_BDF_StartTime":"456828:42:00","n_BDF_VideoSessionID":235,"c_ClientStreamURL":"https://stream.nbcolympics.com/mens-skeleton-heats-3-4"}]},{"n_ParticipantType":1,"n_ParticipantID":1475806,"c_Participant":"MAIER Samuel","c_ParticipantShort":"MAIER S","c_ParticipantFirstName":"Samuel","c_ParticipantLastName":"Maier","c_Bib":"14","n_StartOrder":13,"NOC":{"n_ID":151,"n_GeoID":2219,"c_Name":"Austria","c_Short":"AUT"},"n_Rank":13,"n_RankSort":13,"c_Rank":"13","c_Result":"+3.05","c_ResultAbs":"3:03.54","n_TimeAbs":183540,"n_TimeRel":3050,"c_ODF_QualificationMark":"Q","b_DidNotAdvance":false,"TeamMemberList":[],"ResultPhaseList":[{"n_PhaseID":2412930,"n_Rank":15,"n_RankSort":15,"c_Rank":"15","c_Result":"1:01.36","c_ResultAbs":"1:01.36","n_TimeAbs":61360,"n_TimeRel":1360,"n_BDF_StartTime":1518048014,"c_BDF_StartTime":"456793:56:00","n_BDF_VideoSessionID":233,"c_ClientStreamURL":"https://stream.nbcolympics.com/mens-skeleton-heats-1-2"},{"n_PhaseID":2412931,"n_Rank":11,"n_RankSort":11,"c_Rank":"11","c_Result":"1:01.13","c_ResultAbs":"1:01.13","n_TimeAbs":61130,"n_TimeRel":800,"n_BDF_StartTime":1518048006,"c_BDF_StartTime":"456795:10:00","n_BDF_VideoSessionID":233,"c_ClientStreamURL":"https://stream.nbcolympics.com/mens-skeleton-heats-1-2"},{"n_PhaseID":2412932,"n_Rank":13,"n_RankSort":13,"c_Rank":"13","c_Result":"1:01.05","c_ResultAbs":"1:01.05","n_TimeAbs":61050,"n_TimeRel":890,"n_BDF_StartTime":1518048013,"c_BDF_StartTime":"456828:44:00","n_BDF_VideoSessionID":235,"c_ClientStreamURL":"https://stream.nbcolympics.com/mens-skeleton-heats-3-4"}]},{"n_ParticipantType":1,"n_ParticipantID":1847537,"c_Participant":"WESTON Matt","c_ParticipantShort":"WESTON M","c_ParticipantFirstName":"Matt","c_ParticipantLastName":"Weston","c_Bib":"9","n_StartOrder":14,"NOC":{"n_ID":211,"n_GeoID":4058,"c_Name":"Great Britain","c_Short":"GBR"},"n_Rank":14,"n_RankSort":14,"c_Rank":"14","c_Result":"+3.12","c_ResultAbs":"3:03.61","n_TimeAbs":183610,"n_TimeRel":3120,"c_ODF_QualificationMark":"Q","b_DidNotAdvance":false,"TeamMemberList":[],"ResultPhaseList":[{"n_PhaseID":2412930,"n_Rank":14,"n_RankSort":14,"c_Rank":"14","c_Result":"1:01.34","c_ResultAbs":"1:01.34","n_TimeAbs":61340,"n_TimeRel":1340,"n_BDF_StartTime":1518048009,"c_BDF_StartTime":"456793:46:00","n_BDF_VideoSessionID":233,"c_ClientStreamURL":"https://stream.nbcolympics.com/mens-skeleton-heats-1-2"},{"n_PhaseID":2412931,"n_Rank":12,"n_RankSort":12,"c_Rank":"12","c_Result":"1:01.15","c_ResultAbs":"1:01.15","n_TimeAbs":61150,"n_TimeRel":820,"n_BDF_StartTime":1518048007,"c_BDF_StartTime":"456795:12:00","n_BDF_VideoSessionID":233,"c_ClientStreamURL":"https://stream.nbcolympics.com/mens-skeleton-heats-1-2"},{"n_PhaseID":2412932,"n_Rank":14,"n_RankSort":14,"c_Rank":"14","c_Result":"1:01.12","c_ResultAbs":"1:01.12","n_TimeAbs":61120,"n_TimeRel":960,"n_BDF_StartTime":1518048014,"c_BDF_StartTime":"456828:46:00","n_BDF_VideoSessionID":235,"c_ClientStreamURL":"https://stream.nbcolympics.com/mens-skeleton-heats-3-4"}]},{"n_ParticipantType":1,"n_ParticipantID":834443,"c_Participant":"GASPARI Mattia","c_ParticipantShort":"GASPARI M","c_ParticipantFirstName":"Mattia","c_ParticipantLastName":"Gaspari","c_Bib":"17","n_StartOrder":15,"NOC":{"n_ID":6,"n_GeoID":2210,"c_Name":"Italy","c_Short":"ITA"},"n_Rank":15,"n_RankSort":15,"c_Rank":"15","c_Result":"+3.18","c_ResultAbs":"3:03.67","n_TimeAbs":183670,"n_TimeRel":3180,"c_ODF_QualificationMark":"Q","b_DidNotAdvance":false,"TeamMemberList":[],"ResultPhaseList":[{"n_PhaseID":2412930,"n_Rank":12,"n_RankSort":12,"c_Rank":"12","c_Result":"1:01.20","c_ResultAbs":"1:01.20","n_TimeAbs":61200,"n_TimeRel":1200,"n_BDF_StartTime":1518048017,"c_BDF_StartTime":"456794:02:00","n_BDF_VideoSessionID":233,"c_ClientStreamURL":"https://stream.nbcolympics.com/mens-skeleton-heats-1-2"},{"n_PhaseID":2412931,"n_Rank":15,"n_RankSort":15,"c_Rank":"15","c_Result":"1:01.31","c_ResultAbs":"1:01.31","n_TimeAbs":61310,"n_TimeRel":980,"n_BDF_StartTime":1518048009,"c_BDF_StartTime":"456795:16:00","n_BDF_VideoSessionID":233,"c_ClientStreamURL":"https://stream.nbcolympics.com/mens-skeleton-heats-1-2"},{"n_PhaseID":2412932,"n_Rank":15,"n_RankSort":15,"c_Rank":"15","c_Result":"1:01.16","c_ResultAbs":"1:01.16","n_TimeAbs":61160,"n_TimeRel":1000,"n_BDF_StartTime":1518048015,"c_BDF_StartTime":"456828:48:00","n_BDF_VideoSessionID":235,"c_ClientStreamURL":"https://stream.nbcolympics.com/mens-skeleton-heats-3-4"}]},{"n_ParticipantType":1,"n_ParticipantID":1495443,"c_Participant":"WYATT Marcus","c_ParticipantShort":"WYATT M","c_ParticipantFirstName":"Marcus","c_ParticipantLastName":"Wyatt","c_Bib":"19","n_StartOrder":17,"NOC":{"n_ID":211,"n_GeoID":4058,"c_Name":"Great Britain","c_Short":"GBR"},"n_Rank":16,"n_RankSort":16,"c_Rank":"16","c_Result":"+4.07","c_ResultAbs":"3:04.56","n_TimeAbs":184560,"n_TimeRel":4070,"c_ODF_QualificationMark":"Q","b_DidNotAdvance":false,"TeamMemberList":[],"ResultPhaseList":[{"n_PhaseID":2412930,"n_Rank":16,"n_RankSort":17,"c_Rank":"16","c_Result":"1:01.56","c_ResultAbs":"1:01.56","n_TimeAbs":61560,"n_TimeRel":1560,"n_BDF_StartTime":1518048019,"c_BDF_StartTime":"456794:06:00","n_BDF_VideoSessionID":233,"c_ClientStreamURL":"https://stream.nbcolympics.com/mens-skeleton-heats-1-2"},{"n_PhaseID":2412931,"n_Rank":18,"n_RankSort":18,"c_Rank":"18","c_Result":"1:01.72","c_ResultAbs":"1:01.72","n_TimeAbs":61720,"n_TimeRel":1390,"n_BDF_StartTime":1518048005,"c_BDF_StartTime":"456795:08:00","n_BDF_VideoSessionID":233,"c_ClientStreamURL":"https://stream.nbcolympics.com/mens-skeleton-heats-1-2"},{"n_PhaseID":2412932,"n_Rank":16,"n_RankSort":16,"c_Rank":"16","c_Result":"1:01.28","c_ResultAbs":"1:01.28","n_TimeAbs":61280,"n_TimeRel":1120,"n_BDF_StartTime":1518048017,"c_BDF_StartTime":"456828:52:00","n_BDF_VideoSessionID":235,"c_ClientStreamURL":"https://stream.nbcolympics.com/mens-skeleton-heats-3-4"}]},{"n_ParticipantType":1,"n_ParticipantID":1353104,"c_Participant":"HERASKEVYCH Vladyslav","c_ParticipantShort":"HERASKEVYCH V","c_ParticipantFirstName":"Vladyslav","c_ParticipantLastName":"Heraskevych","c_Bib":"15","n_StartOrder":16,"NOC":{"n_ID":13,"n_GeoID":2232,"c_Name":"Ukraine","c_Short":"UKR"},"n_Rank":17,"n_RankSort":17,"c_Rank":"17","c_Result":"+4.34","c_ResultAbs":"3:04.83","n_TimeAbs":184830,"n_TimeRel":4340,"c_ODF_QualificationMark":"Q","b_DidNotAdvance":false,"TeamMemberList":[],"ResultPhaseList":[{"n_PhaseID":2412930,"n_Rank":18,"n_RankSort":18,"c_Rank":"18","c_Result":"1:01.63","c_ResultAbs":"1:01.63","n_TimeAbs":61630,"n_TimeRel":1630,"n_BDF_StartTime":1518048015,"c_BDF_StartTime":"456793:58:00","n_BDF_VideoSessionID":233,"c_ClientStreamURL":"https://stream.nbcolympics.com/mens-skeleton-heats-1-2"},{"n_PhaseID":2412931,"n_Rank":16,"n_RankSort":16,"c_Rank":"16","c_Result":"1:01.58","c_ResultAbs":"1:01.58","n_TimeAbs":61580,"n_TimeRel":1250,"n_BDF_StartTime":1518048003,"c_BDF_StartTime":"456795:04:00","n_BDF_VideoSessionID":233,"c_ClientStreamURL":"https://stream.nbcolympics.com/mens-skeleton-heats-1-2"},{"n_PhaseID":2412932,"n_Rank":18,"n_RankSort":18,"c_Rank":"18","c_Result":"1:01.62","c_ResultAbs":"1:01.62","n_TimeAbs":61620,"n_TimeRel":1460,"n_BDF_StartTime":1518048016,"c_BDF_StartTime":"456828:50:00","n_BDF_VideoSessionID":235,"c_ClientStreamURL":"https://stream.nbcolympics.com/mens-skeleton-heats-3-4"}]},{"n_ParticipantType":1,"n_ParticipantID":1563857,"c_Participant":"SCHLINTNER Alexander","c_ParticipantShort":"SCHLINTNER A","c_ParticipantFirstName":"Alexander","c_ParticipantLastName":"Schlintner","c_Bib":"20","n_StartOrder":18,"NOC":{"n_ID":151,"n_GeoID":2219,"c_Name":"Austria","c_Short":"AUT"},"n_Rank":18,"n_RankSort":18,"c_Rank":"18","c_Result":"+4.46","c_ResultAbs":"3:04.95","n_TimeAbs":184950,"n_TimeRel":4460,"c_ODF_QualificationMark":"Q","b_DidNotAdvance":false,"TeamMemberList":[],"ResultPhaseList":[{"n_PhaseID":2412930,"n_Rank":16,"n_RankSort":16,"c_Rank":"16","c_Result":"1:01.56","c_ResultAbs":"1:01.56","n_TimeAbs":61560,"n_TimeRel":1560,"n_BDF_StartTime":1518048020,"c_BDF_StartTime":"456794:08:00","n_BDF_VideoSessionID":233,"c_ClientStreamURL":"https://stream.nbcolympics.com/mens-skeleton-heats-1-2"},{"n_PhaseID":2412931,"n_Rank":19,"n_RankSort":19,"c_Rank":"19","c_Result":"1:01.73","c_ResultAbs":"1:01.73","n_TimeAbs":61730,"n_TimeRel":1400,"n_BDF_StartTime":1518048004,"c_BDF_StartTime":"456795:06:00","n_BDF_VideoSessionID":233,"c_ClientStreamURL":"https://stream.nbcolympics.com/mens-skeleton-heats-1-2"},{"n_PhaseID":2412932,"n_Rank":19,"n_RankSort":19,"c_Rank":"19","c_Result":"1:01.66","c_ResultAbs":"1:01.66","n_TimeAbs":61660,"n_TimeRel":1500,"n_BDF_StartTime":1518048018,"c_BDF_StartTime":"456828:54:00","n_BDF_VideoSessionID":235,"c_ClientStreamURL":"https://stream.nbcolympics.com/mens-skeleton-heats-3-4"}]},{"n_ParticipantType":1,"n_ParticipantID":1139516,"c_Participant":"CRUMPTON Nathan","c_ParticipantShort":"CRUMPTON N","c_ParticipantFirstName":"Nathan","c_ParticipantLastName":"Crumpton","c_Bib":"22","n_StartOrder":20,"NOC":{"n_ID":258,"n_GeoID":9600,"c_Name":"American Samoa","c_Short":"ASA"},"n_Rank":19,"n_RankSort":19,"c_Rank":"19","c_Result":"+4.82","c_ResultAbs":"3:05.31","n_TimeAbs":185310,"n_TimeRel":4820,"c_ODF_QualificationMark":"Q","b_DidNotAdvance":false,"TeamMemberList":[],"ResultPhaseList":[{"n_PhaseID":2412930,"n_Rank":22,"n_RankSort":22,"c_Rank":"22","c_Result":"1:02.06","c_ResultAbs":"1:02.06","n_TimeAbs":62060,"n_TimeRel":2060,"n_BDF_StartTime":1518048022,"c_BDF_StartTime":"456794:12:00","n_BDF_VideoSessionID":233,"c_ClientStreamURL":"https://stream.nbcolympics.com/mens-skeleton-heats-1-2"},{"n_PhaseID":2412931,"n_Rank":17,"n_RankSort":17,"c_Rank":"17","c_Result":"1:01.65","c_ResultAbs":"1:01.65","n_TimeAbs":61650,"n_TimeRel":1320,"n_BDF_StartTime":1518048022,"c_BDF_StartTime":"456795:42:00","n_BDF_VideoSessionID":233,"c_ClientStreamURL":"https://stream.nbcolympics.com/mens-skeleton-heats-1-2"},{"n_PhaseID":2412932,"n_Rank":17,"n_RankSort":17,"c_Rank":"17","c_Result":"1:01.60","c_ResultAbs":"1:01.60","n_TimeAbs":61600,"n_TimeRel":1440,"n_BDF_StartTime":1518048020,"c_BDF_StartTime":"456828:58:00","n_BDF_VideoSessionID":235,"c_ClientStreamURL":"https://stream.nbcolympics.com/mens-skeleton-heats-3-4"}]},{"n_ParticipantType":1,"n_ParticipantID":1731352,"c_Participant":"ENZIE Blake","c_ParticipantShort":"ENZIE B","c_ParticipantFirstName":"Blake","c_ParticipantLastName":"Enzie","c_Bib":"24","n_StartOrder":19,"NOC":{"n_ID":159,"n_GeoID":2231,"c_Name":"Canada","c_Short":"CAN"},"n_Rank":20,"n_RankSort":20,"c_Rank":"20","c_Result":"+4.85","c_ResultAbs":"3:05.34","n_TimeAbs":185340,"n_TimeRel":4850,"c_ODF_QualificationMark":"Q","b_DidNotAdvance":false,"TeamMemberList":[],"ResultPhaseList":[{"n_PhaseID":2412930,"n_Rank":19,"n_RankSort":19,"c_Rank":"19","c_Result":"1:01.65","c_ResultAbs":"1:01.65","n_TimeAbs":61650,"n_TimeRel":1650,"n_BDF_StartTime":1518048024,"c_BDF_StartTime":"456794:16:00","n_BDF_VideoSessionID":233,"c_ClientStreamURL":"https://stream.nbcolympics.com/mens-skeleton-heats-1-2"},{"n_PhaseID":2412931,"n_Rank":20,"n_RankSort":20,"c_Rank":"20","c_Result":"1:01.76","c_ResultAbs":"1:01.76","n_TimeAbs":61760,"n_TimeRel":1430,"n_BDF_StartTime":1518048002,"c_BDF_StartTime":"456795:02:00","n_BDF_VideoSessionID":233,"c_ClientStreamURL":"https://stream.nbcolympics.com/mens-skeleton-heats-1-2"},{"n_PhaseID":2412932,"n_Rank":21,"n_RankSort":21,"c_Rank":"21","c_Result":"1:01.93","c_ResultAbs":"1:01.93","n_TimeAbs":61930,"n_TimeRel":1770,"n_BDF_StartTime":1518048019,"c_BDF_StartTime":"456828:56:00","n_BDF_VideoSessionID":235,"c_ClientStreamURL":"https://stream.nbcolympics.com/mens-skeleton-heats-3-4"}]},{"n_ParticipantType":1,"n_ParticipantID":1482343,"c_Participant":"BLASER Andrew","c_ParticipantShort":"BLASER A","c_ParticipantFirstName":"Andrew","c_ParticipantLastName":"Blaser","c_Bib":"2","n_StartOrder":21,"NOC":{"n_ID":5,"n_GeoID":2209,"c_Name":"United States","c_Short":"USA"},"n_Rank":21,"n_RankSort":21,"c_Rank":"21","c_Result":"+5.49","c_ResultAbs":"3:05.98","n_TimeAbs":185980,"n_TimeRel":5490,"b_DidNotAdvance":false,"TeamMemberList":[],"ResultPhaseList":[{"n_PhaseID":2412930,"n_Rank":20,"n_RankSort":20,"c_Rank":"20","c_Result":"1:01.80","c_ResultAbs":"1:01.80","n_TimeAbs":61800,"n_TimeRel":1800,"n_BDF_StartTime":1518048002,"c_BDF_StartTime":"456793:32:00","n_BDF_VideoSessionID":233,"c_ClientStreamURL":"https://stream.nbcolympics.com/mens-skeleton-heats-1-2"},{"n_PhaseID":2412931,"n_Rank":21,"n_RankSort":21,"c_Rank":"21","c_Result":"1:02.08","c_ResultAbs":"1:02.08","n_TimeAbs":62080,"n_TimeRel":1750,"n_BDF_StartTime":1518048001,"c_BDF_StartTime":"456795:00:00","n_BDF_VideoSessionID":233,"c_ClientStreamURL":"https://stream.nbcolympics.com/mens-skeleton-heats-1-2"},{"n_PhaseID":2412932,"n_Rank":22,"n_RankSort":22,"c_Rank":"22","c_Result":"1:02.10","c_ResultAbs":"1:02.10","n_TimeAbs":62100,"n_TimeRel":1940,"n_BDF_StartTime":1518048021,"c_BDF_StartTime":"456829:00:00","n_BDF_VideoSessionID":235,"c_ClientStreamURL":"https://stream.nbcolympics.com/mens-skeleton-heats-3-4"}]},{"n_ParticipantType":1,"n_ParticipantID":1234238,"c_Participant":"SIEBER Basil","c_ParticipantShort":"SIEBER B","c_ParticipantFirstName":"Basil","c_ParticipantLastName":"Sieber","c_Bib":"25","n_StartOrder":22,"NOC":{"n_ID":149,"n_GeoID":2213,"c_Name":"Switzerland","c_Short":"SUI"},"n_Rank":22,"n_RankSort":22,"c_Rank":"22","c_Result":"+6.34","c_ResultAbs":"3:06.83","n_TimeAbs":186830,"n_TimeRel":6340,"b_DidNotAdvance":false,"TeamMemberList":[],"ResultPhaseList":[{"n_PhaseID":2412930,"n_Rank":21,"n_RankSort":21,"c_Rank":"21","c_Result":"1:01.95","c_ResultAbs":"1:01.95","n_TimeAbs":61950,"n_TimeRel":1950,"n_BDF_StartTime":1518048025,"c_BDF_StartTime":"456794:18:00","n_BDF_VideoSessionID":233,"c_ClientStreamURL":"https://stream.nbcolympics.com/mens-skeleton-heats-1-2"},{"n_PhaseID":2412931,"n_Rank":22,"n_RankSort":22,"c_Rank":"22","c_Result":"1:02.16","c_ResultAbs":"1:02.16","n_TimeAbs":62160,"n_TimeRel":1830,"n_BDF_StartTime":1518048021,"c_BDF_StartTime":"456795:40:00","n_BDF_VideoSessionID":233,"c_ClientStreamURL":"https://stream.nbcolympics.com/mens-skeleton-heats-1-2"},{"n_PhaseID":2412932,"n_Rank":25,"n_RankSort":25,"c_Rank":"25","c_Result":"1:02.72","c_ResultAbs":"1:02.72","n_TimeAbs":62720,"n_TimeRel":2560,"n_BDF_StartTime":1518048022,"c_BDF_StartTime":"456829:02:00","n_BDF_VideoSessionID":235,"c_ClientStreamURL":"https://stream.nbcolympics.com/mens-skeleton-heats-3-4"}]},{"n_ParticipantType":1,"n_ParticipantID":1939038,"c_Participant":"ROMANOV Daniil","c_ParticipantShort":"ROMANOV D","c_ParticipantFirstName":"Daniil","c_ParticipantLastName":"Romanov","c_Bib":"3","n_StartOrder":23,"NOC":{"n_ID":23062,"n_GeoID":73035,"c_Name":"ROC","c_Short":"ROC"},"n_Rank":23,"n_RankSort":23,"c_Rank":"23","c_Result":"+6.78","c_ResultAbs":"3:07.27","n_TimeAbs":187270,"n_TimeRel":6780,"b_DidNotAdvance":false,"TeamMemberList":[],"ResultPhaseList":[{"n_PhaseID":2412930,"n_Rank":24,"n_RankSort":24,"c_Rank":"24","c_Result":"1:02.47","c_ResultAbs":"1:02.47","n_TimeAbs":62470,"n_TimeRel":2470,"n_BDF_StartTime":1518048003,"c_BDF_StartTime":"456793:34:00","n_BDF_VideoSessionID":233,"c_ClientStreamURL":"https://stream.nbcolympics.com/mens-skeleton-heats-1-2"},{"n_PhaseID":2412931,"n_Rank":23,"n_RankSort":23,"c_Rank":"23","c_Result":"1:02.60","c_ResultAbs":"1:02.60","n_TimeAbs":62600,"n_TimeRel":2270,"n_BDF_StartTime":1518048024,"c_BDF_StartTime":"456795:46:00","n_BDF_VideoSessionID":233,"c_ClientStreamURL":"https://stream.nbcolympics.com/mens-skeleton-heats-1-2"},{"n_PhaseID":2412932,"n_Rank":23,"n_RankSort":23,"c_Rank":"23","c_Result":"1:02.20","c_ResultAbs":"1:02.20","n_TimeAbs":62200,"n_TimeRel":2040,"n_BDF_StartTime":1518048023,"c_BDF_StartTime":"456829:04:00","n_BDF_VideoSessionID":235,"c_ClientStreamURL":"https://stream.nbcolympics.com/mens-skeleton-heats-3-4"}]},{"n_ParticipantType":1,"n_ParticipantID":658631,"c_Participant":"MIRAMBELL Ander","c_ParticipantShort":"MIRAMBELL A","c_ParticipantFirstName":"Ander","c_ParticipantLastName":"Mirambell","c_Bib":"1","n_StartOrder":24,"NOC":{"n_ID":145,"n_GeoID":2203,"c_Name":"Spain","c_Short":"ESP"},"n_Rank":24,"n_RankSort":24,"c_Rank":"24","c_Result":"+7.66","c_ResultAbs":"3:08.15","n_TimeAbs":188150,"n_TimeRel":7660,"b_DidNotAdvance":false,"TeamMemberList":[],"ResultPhaseList":[{"n_PhaseID":2412930,"n_Rank":23,"n_RankSort":23,"c_Rank":"23","c_Result":"1:02.45","c_ResultAbs":"1:02.45","n_TimeAbs":62450,"n_TimeRel":2450,"n_BDF_StartTime":1518048001,"c_BDF_StartTime":"456793:30:00","n_BDF_VideoSessionID":233,"c_ClientStreamURL":"https://stream.nbcolympics.com/mens-skeleton-heats-1-2"},{"n_PhaseID":2412931,"n_Rank":25,"n_RankSort":25,"c_Rank":"25","c_Result":"1:03.36","c_ResultAbs":"1:03.36","n_TimeAbs":63360,"n_TimeRel":3030,"n_BDF_StartTime":1518048023,"c_BDF_StartTime":"456795:44:00","n_BDF_VideoSessionID":233,"c_ClientStreamURL":"https://stream.nbcolympics.com/mens-skeleton-heats-1-2"},{"n_PhaseID":2412932,"n_Rank":24,"n_RankSort":24,"c_Rank":"24","c_Result":"1:02.34","c_ResultAbs":"1:02.34","n_TimeAbs":62340,"n_TimeRel":2180,"n_BDF_StartTime":1518048024,"c_BDF_StartTime":"456829:06:00","n_BDF_VideoSessionID":235,"c_ClientStreamURL":"https://stream.nbcolympics.com/mens-skeleton-heats-3-4"}]},{"n_ParticipantType":1,"n_ParticipantID":1125020,"c_Participant":"TIMMINGS Nicholas","c_ParticipantShort":"TIMMINGS N","c_ParticipantFirstName":"Nicholas","c_ParticipantLastName":"Timmings","c_Bib":"23","n_StartOrder":25,"NOC":{"n_ID":157,"n_GeoID":2229,"c_Name":"Australia","c_Short":"AUS"},"n_Rank":25,"n_RankSort":25,"c_Rank":"25","c_Result":"+7.88","c_ResultAbs":"3:08.37","n_TimeAbs":188370,"n_TimeRel":7880,"b_DidNotAdvance":false,"TeamMemberList":[],"ResultPhaseList":[{"n_PhaseID":2412930,"n_Rank":25,"n_RankSort":25,"c_Rank":"25","c_Result":"1:03.76","c_ResultAbs":"1:03.76","n_TimeAbs":63760,"n_TimeRel":3760,"n_BDF_StartTime":1518048023,"c_BDF_StartTime":"456794:14:00","n_BDF_VideoSessionID":233,"c_ClientStreamURL":"https://stream.nbcolympics.com/mens-skeleton-heats-1-2"},{"n_PhaseID":2412931,"n_Rank":24,"n_RankSort":24,"c_Rank":"24","c_Result":"1:02.83","c_ResultAbs":"1:02.83","n_TimeAbs":62830,"n_TimeRel":2500,"n_BDF_StartTime":1518048025,"c_BDF_StartTime":"456795:48:00","n_BDF_VideoSessionID":233,"c_ClientStreamURL":"https://stream.nbcolympics.com/mens-skeleton-heats-1-2"},{"n_PhaseID":2412932,"n_Rank":20,"n_RankSort":20,"c_Rank":"20","c_Result":"1:01.78","c_ResultAbs":"1:01.78","n_TimeAbs":61780,"n_TimeRel":1620,"n_BDF_StartTime":1518048025,"c_BDF_StartTime":"456829:08:00","n_BDF_VideoSessionID":235,"c_ClientStreamURL":"https://stream.nbcolympics.com/mens-skeleton-heats-3-4"}]}]},"Summary":{"Phase":{},"ParticipantList":[]},"Legend":[{"c_Name":"CANCEL","c_Description":"Cancelled"},{"c_Name":"DNF","c_Description":"Did Not Finish"},{"c_Name":"DNS","c_Description":"Did Not Start"},{"c_Name":"DQB","c_Description":"Disqualified For Unsportsmanlike Behavior"},{"c_Name":"DSQ","c_Description":"Disqualified"},{"c_Name":"Q","c_Description":"Qualified"}]}
